{"assets":{"C393C2EE41E57BBAC6C8BC0FFE7B88CA":{"type":"texture","index":9,"url":{"native":"assets\/99DF9EF2-0438-4D45-986E-04903D0F5FF8.pdf"},"width":1024,"height":768},"51362B679AAC4739143AF2ABA5836914":{"type":"texture","index":6,"url":{"native":"assets\/99DF9EF2-0438-4D45-986E-04903D0F5FF8.pdf"},"width":968,"height":135},"DC9A3BA08A4D9EB735DA96258A475113":{"type":"texture","index":3,"url":{"native":"assets\/99DF9EF2-0438-4D45-986E-04903D0F5FF8.pdf"},"width":968,"height":91},"95D7342E436EC3FA033869266AFFF539":{"type":"texture","index":2,"url":{"native":"assets\/99DF9EF2-0438-4D45-986E-04903D0F5FF8.pdf"},"width":26,"height":21},"75BD6FF36F5358FE23CA21DC0E2B2B59":{"type":"texture","index":7,"url":{"native":"assets\/99DF9EF2-0438-4D45-986E-04903D0F5FF8.pdf"},"width":966,"height":86},"BF223A31E7255648FF4367CA0B6DC93E":{"type":"texture","index":4,"url":{"native":"assets\/99DF9EF2-0438-4D45-986E-04903D0F5FF8.pdf"},"width":968,"height":87},"2AC635A1B91F79381B7DC140DF8EC6FD":{"type":"texture","index":5,"url":{"native":"assets\/99DF9EF2-0438-4D45-986E-04903D0F5FF8.pdf"},"width":968,"height":85},"9251636AE7EC24F2536617C9E7909BA3":{"type":"texture","index":0,"url":{"native":"assets\/99DF9EF2-0438-4D45-986E-04903D0F5FF8.pdf"},"width":1024,"height":768},"D0EB9A94DA96765B0A159C469B4E3EAB":{"type":"texture","index":8,"url":{"native":"assets\/99DF9EF2-0438-4D45-986E-04903D0F5FF8.pdf"},"width":1024,"height":768},"58B928AAF0171AFA33A1A9DB076B54DF":{"type":"texture","index":1,"url":{"native":"assets\/99DF9EF2-0438-4D45-986E-04903D0F5FF8.pdf"},"width":578,"height":38}},"events":[{"effects":[{"beginTime":0,"baseLayer":{"animations":[],"initialState":{"affineTransform":[1,0,0,1,0,0],"masksToBounds":false,"rotation":0,"scale":1,"position":{"pointX":516,"pointY":179.04168701171875},"width":968,"sublayerTransform":[1,0,0,0,0,1,0,0,0,0,1,0,0,0,0,1],"contentsRect":{"y":0,"x":0,"width":1,"height":1},"opacity":1,"edgeAntialiasingMask":251658240,"height":91,"hidden":false,"anchorPoint":{"pointX":0.5,"pointY":0.5}},"objectID":"8EB51A19-E110-4214-8053-342AEA12F7AC","layers":[{"animations":[],"initialState":{"affineTransform":[1,0,0,1,0,0],"masksToBounds":false,"rotation":0,"scale":1,"position":{"pointX":480,"pointY":250.45831298828125},"width":968,"sublayerTransform":[1,0,0,0,0,1,0,0,0,0,1,-0.00049229876906403734,0,0,0,1],"contentsRect":{"y":0,"x":0,"width":1,"height":1},"opacity":1,"edgeAntialiasingMask":251658240,"height":91,"hidden":false,"anchorPoint":{"pointX":0.49586776859504134,"pointY":2.7522891537173764}},"layers":[{"animations":[{"additive":false,"timeOffset":0,"beginTime":1e-100,"repeatCount":0,"fillMode":"both","duration":0.001,"autoreverses":false,"animations":[{"additive":false,"timeOffset":0,"beginTime":0,"from":{"scalar":true},"repeatCount":0,"fillMode":"both","duration":0.0001,"autoreverses":false,"property":"hidden","to":{"scalar":false},"removedOnCompletion":true},{"additive":false,"timeOffset":0,"beginTime":0.0001,"from":{"scalar":false},"repeatCount":0,"fillMode":"forwards","duration":0.00089999999999999998,"autoreverses":false,"property":"hidden","to":{"scalar":false},"removedOnCompletion":true}],"removedOnCompletion":false}],"layers":[],"texturedRectangle":{"isBackgroundTexture":true,"singleTextureOpacity":1,"textureType":5,"textBaseline":0,"textXHeight":0,"isVerticalText":false},"initialState":{"affineTransform":[1,0,0,1,0,0],"masksToBounds":false,"rotation":0,"scale":1,"position":{"pointX":480,"pointY":41.95831298828125},"width":968,"sublayerTransform":[1,0,0,0,0,1,0,0,0,0,1,0,0,0,0,1],"contentsRect":{"y":0,"x":0,"width":1,"height":1},"opacity":1,"edgeAntialiasingMask":0,"height":91,"hidden":true,"anchorPoint":{"pointX":0.5,"pointY":0.5}},"texture":"DC9A3BA08A4D9EB735DA96258A475113"}]}]},"effects":[],"duration":0.001,"type":"buildIn","attributes":{"direction":0},"name":"apple:appear","objectID":"8EB51A19-E110-4214-8053-342AEA12F7AC"}],"automaticPlay":false,"hyperlinks":[],"accessibility":[{"text":"equation.pdf","targetRectangle":{"y":460.93682861328125,"x":346.1990309553442,"width":20.787277030323764,"height":33.316556337194697}},{"text":"Given a Markov kernel ￼ can construct a chain ￼ by iterating over ￼","targetRectangle":{"y":354.33309936523438,"x":61.654824018478394,"width":707.51718353084277,"height":33.373817505419026}},{"text":"equation.pdf","targetRectangle":{"y":511.54714965820312,"x":348.41738891601562,"width":282.74505945299848,"height":25.38674860604101}},{"text":"The marginal law ￼ of ￼ after ￼ steps satisfies","targetRectangle":{"y":460.93682861328125,"x":131.65482401847839,"width":435.89900733167542,"height":33.316556337194697}},{"text":"equation.pdf","targetRectangle":{"y":195.43658447265625,"x":291.46875,"width":404.70209024355131,"height":23.811000000000007}},{"text":"equation.pdf","targetRectangle":{"y":408.95050048828125,"x":412.14752197265625,"width":163.77309745094021,"height":23.520248598083867}},{"text":"￼","targetRectangle":{"y":66.408382415771484,"x":964.57660043239594,"width":23.0390625,"height":28}},{"text":"Given a Markov chain defines a Markov kernel as the one step transition","targetRectangle":{"y":238.13603210449219,"x":97.764708280563354,"width":679.18399999999974,"height":26.361846923828125}},{"text":"equation.pdf","targetRectangle":{"y":460.93682861328125,"x":297.53482401847839,"width":18.502206936865832,"height":33.316556337194697}},{"text":"equation.pdf","targetRectangle":{"y":291.52666219037121,"x":280.09764494433477,"width":425.71490623288685,"height":23.810999999999979}},{"text":"Markov kernels v4: Markov chains","targetRectangle":{"y":56.908382415771484,"x":36,"width":578.44800000000009,"height":48.400146484375}},{"text":"equation.pdf","targetRectangle":{"y":634.04052734375,"x":296.219970703125,"width":436.3112914620815,"height":68.98475017285341}},{"text":"equation.pdf","targetRectangle":{"y":354.33309936523438,"x":696.35318048805425,"width":72.818827061266916,"height":33.373817505419026}},{"text":"equation.pdf","targetRectangle":{"y":354.33309936523438,"x":278.20082401847839,"width":17.931079439252358,"height":31.721952634437059}},{"text":"equation.pdf","targetRectangle":{"y":137.54168701171875,"x":623.94273072106353,"width":20.646280373831814,"height":31.721952634437059}},{"text":"equation.pdf","targetRectangle":{"y":137.54168701171875,"x":219.40470828056334,"width":153.93602244050032,"height":33.373817505419026}},{"text":"The joint law of ￼ ","targetRectangle":{"y":577.320068359375,"x":133.87459063529968,"width":337.97634477694891,"height":33.37381750541897}},{"text":"A Markov Chain ￼ is a stochastic process in ￼ such that ","targetRectangle":{"y":137.54168701171875,"x":62.764708280563354,"width":682.05630281433173,"height":33.373817505419026}},{"text":"equation.pdf","targetRectangle":{"y":577.320068359375,"x":282.22059063529969,"width":183.51434477694892,"height":33.37381750541897}},{"text":"equation.pdf","targetRectangle":{"y":460.93682861328125,"x":421.19430798566793,"width":7.4735233644859704,"height":31.721952634437059}},{"text":"equation.pdf","targetRectangle":{"y":354.33309936523438,"x":512.54590345773079,"width":20.787277030323708,"height":33.316556337194697}}],"baseLayer":{"animations":[],"initialState":{"affineTransform":[1,0,0,1,0,0],"masksToBounds":false,"rotation":0,"scale":1,"position":{"pointX":512,"pointY":384},"width":1024,"sublayerTransform":[1,0,0,0,0,1,0,0,0,0,1,0,0,0,0,1],"contentsRect":{"y":0,"x":0,"width":1,"height":1},"opacity":1,"edgeAntialiasingMask":251658240,"height":768,"hidden":false,"anchorPoint":{"pointX":0.5,"pointY":0.5}},"layers":[{"animations":[],"initialState":{"affineTransform":[1,0,0,1,0,0],"masksToBounds":false,"rotation":0,"scale":1,"position":{"pointX":512,"pointY":384},"width":1024,"sublayerTransform":[1,0,0,0,0,1,0,0,0,0,1,0,0,0,0,1],"contentsRect":{"y":0,"x":0,"width":1,"height":1},"opacity":1,"edgeAntialiasingMask":251658240,"height":768,"hidden":false,"anchorPoint":{"pointX":0.5,"pointY":0.5}},"layers":[{"animations":[],"initialState":{"affineTransform":[1,0,0,1,0,0],"masksToBounds":false,"rotation":0,"scale":1,"position":{"pointX":512,"pointY":384},"width":1024,"sublayerTransform":[1,0,0,0,0,1,0,0,0,0,1,0,0,0,0,1],"contentsRect":{"y":0,"x":0,"width":1,"height":1},"opacity":1,"edgeAntialiasingMask":251658240,"height":768,"hidden":false,"anchorPoint":{"pointX":0.5,"pointY":0.5}},"layers":[{"animations":[],"layers":[],"texturedRectangle":{"isBackgroundTexture":true,"singleTextureOpacity":1,"textureType":1,"textBaseline":0,"textXHeight":0,"isVerticalText":false},"initialState":{"affineTransform":[1,0,0,1,0,0],"masksToBounds":false,"rotation":0,"scale":1,"position":{"pointX":512,"pointY":384},"width":1024,"sublayerTransform":[1,0,0,0,0,1,0,0,0,0,1,0,0,0,0,1],"contentsRect":{"y":0,"x":0,"width":1,"height":1},"opacity":1,"edgeAntialiasingMask":0,"height":768,"hidden":false,"anchorPoint":{"pointX":0.5,"pointY":0.5}},"texture":"9251636AE7EC24F2536617C9E7909BA3"}]}]},{"animations":[],"initialState":{"affineTransform":[1,0,0,1,0,0],"masksToBounds":false,"rotation":0,"scale":1,"position":{"pointX":512,"pointY":384},"width":1024,"sublayerTransform":[1,0,0,0,0,1,0,0,0,0,1,0,0,0,0,1],"contentsRect":{"y":0,"x":0,"width":1,"height":1},"opacity":1,"edgeAntialiasingMask":251658240,"height":768,"hidden":false,"anchorPoint":{"pointX":0.5,"pointY":0.5}},"layers":[{"animations":[],"initialState":{"affineTransform":[1,0,0,1,0,0],"masksToBounds":false,"rotation":0,"scale":1,"position":{"pointX":321,"pointY":71.908382415771484},"width":578,"sublayerTransform":[1,0,0,0,0,1,0,0,0,0,1,0,0,0,0,1],"contentsRect":{"y":0,"x":0,"width":1,"height":1},"opacity":1,"edgeAntialiasingMask":251658240,"height":38,"hidden":false,"anchorPoint":{"pointX":0.5,"pointY":0.5}},"layers":[{"animations":[],"layers":[],"texturedRectangle":{"singleTextureOpacity":1,"textXHeight":0.640421052631579,"textBaseline":0.96012627451043375,"isBackgroundTexture":true,"isVerticalText":false,"textColor":[0.46666663885116577,0.113725446164608,0.46274513006210327,1],"textureType":6},"initialState":{"affineTransform":[1,0,0,1,0,0],"masksToBounds":false,"rotation":0,"scale":1,"position":{"pointX":294,"pointY":21.091617584228516},"width":578,"sublayerTransform":[1,0,0,0,0,1,0,0,0,0,1,0,0,0,0,1],"contentsRect":{"y":0,"x":0,"width":1,"height":1},"opacity":1,"edgeAntialiasingMask":0,"height":38,"hidden":false,"anchorPoint":{"pointX":0.5,"pointY":0.5}},"texture":"58B928AAF0171AFA33A1A9DB076B54DF"}]}]},{"animations":[],"initialState":{"affineTransform":[1,0,0,1,0,0],"masksToBounds":false,"rotation":0,"scale":1,"position":{"pointX":512,"pointY":384},"width":1024,"sublayerTransform":[1,0,0,0,0,1,0,0,0,0,1,0,0,0,0,1],"contentsRect":{"y":0,"x":0,"width":1,"height":1},"opacity":1,"edgeAntialiasingMask":251658240,"height":768,"hidden":false,"anchorPoint":{"pointX":0.5,"pointY":0.5}},"layers":[{"animations":[],"initialState":{"affineTransform":[1,0,0,1,0,0],"masksToBounds":false,"rotation":0,"scale":1,"position":{"pointX":972.57660043239594,"pointY":72.908382415771484},"width":26,"sublayerTransform":[1,0,0,0,0,1,0,0,0,0,1,0,0,0,0,1],"contentsRect":{"y":0,"x":0,"width":1,"height":1},"opacity":1,"edgeAntialiasingMask":251658240,"height":21,"hidden":false,"anchorPoint":{"pointX":0.5,"pointY":0.5}},"layers":[{"animations":[],"layers":[],"texturedRectangle":{"singleTextureOpacity":1,"textXHeight":0.8203125,"textBaseline":0.90393338884626118,"isBackgroundTexture":true,"isVerticalText":false,"textColor":[0.65252363681793213,0.66733616590499878,0.66081041097640991,1],"textureType":6},"initialState":{"affineTransform":[1,0,0,1,0,0],"masksToBounds":false,"rotation":0,"scale":1,"position":{"pointX":16.423399567604065,"pointY":18.091617584228516},"width":26,"sublayerTransform":[1,0,0,0,0,1,0,0,0,0,1,0,0,0,0,1],"contentsRect":{"y":0,"x":0,"width":1,"height":1},"opacity":1,"edgeAntialiasingMask":0,"height":21,"hidden":false,"anchorPoint":{"pointX":0.5,"pointY":0.5}},"texture":"95D7342E436EC3FA033869266AFFF539"}]}]},{"animations":[],"initialState":{"affineTransform":[1,0,0,1,0,0],"masksToBounds":false,"rotation":0,"scale":1,"position":{"pointX":512,"pointY":384},"width":1024,"sublayerTransform":[1,0,0,0,0,1,0,0,0,0,1,0,0,0,0,1],"contentsRect":{"y":0,"x":0,"width":1,"height":1},"opacity":1,"edgeAntialiasingMask":251658240,"height":768,"hidden":false,"anchorPoint":{"pointX":0.5,"pointY":0.5}},"layers":[{"animations":[],"initialState":{"affineTransform":[1,0,0,1,0,0],"masksToBounds":false,"rotation":0,"scale":1,"position":{"pointX":516,"pointY":179.04168701171875},"width":968,"sublayerTransform":[1,0,0,0,0,1,0,0,0,0,1,0,0,0,0,1],"contentsRect":{"y":0,"x":0,"width":1,"height":1},"opacity":1,"edgeAntialiasingMask":251658240,"height":91,"hidden":false,"anchorPoint":{"pointX":0.5,"pointY":0.5}},"objectID":"8EB51A19-E110-4214-8053-342AEA12F7AC","layers":[{"animations":[],"layers":[],"texturedRectangle":{"isBackgroundTexture":true,"singleTextureOpacity":1,"textureType":5,"textBaseline":0,"textXHeight":0,"isVerticalText":false},"initialState":{"affineTransform":[1,0,0,1,0,0],"masksToBounds":false,"rotation":0,"scale":1,"position":{"pointX":480,"pointY":41.95831298828125},"width":968,"sublayerTransform":[1,0,0,0,0,1,0,0,0,0,1,0,0,0,0,1],"contentsRect":{"y":0,"x":0,"width":1,"height":1},"opacity":1,"edgeAntialiasingMask":0,"height":91,"hidden":true,"anchorPoint":{"pointX":0.5,"pointY":0.5}},"texture":"DC9A3BA08A4D9EB735DA96258A475113"}]}]},{"animations":[],"initialState":{"affineTransform":[1,0,0,1,0,0],"masksToBounds":false,"rotation":0,"scale":1,"position":{"pointX":512,"pointY":384},"width":1024,"sublayerTransform":[1,0,0,0,0,1,0,0,0,0,1,0,0,0,0,1],"contentsRect":{"y":0,"x":0,"width":1,"height":1},"opacity":1,"edgeAntialiasingMask":251658240,"height":768,"hidden":false,"anchorPoint":{"pointX":0.5,"pointY":0.5}},"layers":[{"animations":[],"initialState":{"affineTransform":[1,0,0,1,0,0],"masksToBounds":false,"rotation":0,"scale":1,"position":{"pointX":514.89011573791504,"pointY":393.83309936523438},"width":968,"sublayerTransform":[1,0,0,0,0,1,0,0,0,0,1,0,0,0,0,1],"contentsRect":{"y":0,"x":0,"width":1,"height":1},"opacity":1,"edgeAntialiasingMask":251658240,"height":87,"hidden":false,"anchorPoint":{"pointX":0.5,"pointY":0.5}},"objectID":"6E97E328-7C58-4ECD-BD54-4E2DE3E7B534","layers":[{"animations":[],"layers":[],"texturedRectangle":{"isBackgroundTexture":true,"singleTextureOpacity":1,"textureType":5,"textBaseline":0,"textXHeight":0,"isVerticalText":false},"initialState":{"affineTransform":[1,0,0,1,0,0],"masksToBounds":false,"rotation":0,"scale":1,"position":{"pointX":480.10988426208496,"pointY":40.166900634765625},"width":968,"sublayerTransform":[1,0,0,0,0,1,0,0,0,0,1,0,0,0,0,1],"contentsRect":{"y":0,"x":0,"width":1,"height":1},"opacity":1,"edgeAntialiasingMask":0,"height":87,"hidden":true,"anchorPoint":{"pointX":0.5,"pointY":0.5}},"texture":"BF223A31E7255648FF4367CA0B6DC93E"}]}]},{"animations":[],"initialState":{"affineTransform":[1,0,0,1,0,0],"masksToBounds":false,"rotation":0,"scale":1,"position":{"pointX":512,"pointY":384},"width":1024,"sublayerTransform":[1,0,0,0,0,1,0,0,0,0,1,0,0,0,0,1],"contentsRect":{"y":0,"x":0,"width":1,"height":1},"opacity":1,"edgeAntialiasingMask":251658240,"height":768,"hidden":false,"anchorPoint":{"pointX":0.5,"pointY":0.5}},"layers":[{"animations":[],"initialState":{"affineTransform":[1,0,0,1,0,0],"masksToBounds":false,"rotation":0,"scale":1,"position":{"pointX":514.89011573791504,"pointY":499.43682861328125},"width":968,"sublayerTransform":[1,0,0,0,0,1,0,0,0,0,1,0,0,0,0,1],"contentsRect":{"y":0,"x":0,"width":1,"height":1},"opacity":1,"edgeAntialiasingMask":251658240,"height":85,"hidden":false,"anchorPoint":{"pointX":0.5,"pointY":0.5}},"objectID":"2D2998DE-7084-4730-A789-BB46D87301FC","layers":[{"animations":[],"layers":[],"texturedRectangle":{"isBackgroundTexture":true,"singleTextureOpacity":1,"textureType":5,"textBaseline":0,"textXHeight":0,"isVerticalText":false},"initialState":{"affineTransform":[1,0,0,1,0,0],"masksToBounds":false,"rotation":0,"scale":1,"position":{"pointX":480.10988426208496,"pointY":38.56317138671875},"width":968,"sublayerTransform":[1,0,0,0,0,1,0,0,0,0,1,0,0,0,0,1],"contentsRect":{"y":0,"x":0,"width":1,"height":1},"opacity":1,"edgeAntialiasingMask":0,"height":85,"hidden":true,"anchorPoint":{"pointX":0.5,"pointY":0.5}},"texture":"2AC635A1B91F79381B7DC140DF8EC6FD"}]}]},{"animations":[],"initialState":{"affineTransform":[1,0,0,1,0,0],"masksToBounds":false,"rotation":0,"scale":1,"position":{"pointX":512,"pointY":384},"width":1024,"sublayerTransform":[1,0,0,0,0,1,0,0,0,0,1,0,0,0,0,1],"contentsRect":{"y":0,"x":0,"width":1,"height":1},"opacity":1,"edgeAntialiasingMask":251658240,"height":768,"hidden":false,"anchorPoint":{"pointX":0.5,"pointY":0.5}},"layers":[{"animations":[],"initialState":{"affineTransform":[1,0,0,1,0,0],"masksToBounds":false,"rotation":0,"scale":1,"position":{"pointX":517.10988235473633,"pointY":640.820068359375},"width":968,"sublayerTransform":[1,0,0,0,0,1,0,0,0,0,1,0,0,0,0,1],"contentsRect":{"y":0,"x":0,"width":1,"height":1},"opacity":1,"edgeAntialiasingMask":251658240,"height":135,"hidden":false,"anchorPoint":{"pointX":0.5,"pointY":0.5}},"objectID":"32BD2261-3E37-460F-B23A-521CCBCDB33F","layers":[{"animations":[],"layers":[],"texturedRectangle":{"isBackgroundTexture":true,"singleTextureOpacity":1,"textureType":5,"textBaseline":0,"textXHeight":0,"isVerticalText":false},"initialState":{"affineTransform":[1,0,0,1,0,0],"masksToBounds":false,"rotation":0,"scale":1,"position":{"pointX":479.89011764526367,"pointY":64.179931640625},"width":968,"sublayerTransform":[1,0,0,0,0,1,0,0,0,0,1,0,0,0,0,1],"contentsRect":{"y":0,"x":0,"width":1,"height":1},"opacity":1,"edgeAntialiasingMask":0,"height":135,"hidden":true,"anchorPoint":{"pointX":0.5,"pointY":0.5}},"texture":"51362B679AAC4739143AF2ABA5836914"}]}]},{"animations":[],"initialState":{"affineTransform":[1,0,0,1,0,0],"masksToBounds":false,"rotation":0,"scale":1,"position":{"pointX":512,"pointY":384},"width":1024,"sublayerTransform":[1,0,0,0,0,1,0,0,0,0,1,0,0,0,0,1],"contentsRect":{"y":0,"x":0,"width":1,"height":1},"opacity":1,"edgeAntialiasingMask":251658240,"height":768,"hidden":false,"anchorPoint":{"pointX":0.5,"pointY":0.5}},"layers":[{"animations":[],"initialState":{"affineTransform":[1,0,0,1,0,0],"masksToBounds":false,"rotation":0,"scale":1,"position":{"pointX":515,"pointY":277.13603210449219},"width":966,"sublayerTransform":[1,0,0,0,0,1,0,0,0,0,1,0,0,0,0,1],"contentsRect":{"y":0,"x":0,"width":1,"height":1},"opacity":1,"edgeAntialiasingMask":251658240,"height":86,"hidden":false,"anchorPoint":{"pointX":0.5,"pointY":0.5}},"objectID":"98B8DDAD-86E4-4739-A0DA-7C1153DB4A89","layers":[{"animations":[],"layers":[],"texturedRectangle":{"isBackgroundTexture":true,"singleTextureOpacity":1,"textureType":5,"textBaseline":0,"textXHeight":0,"isVerticalText":false},"initialState":{"affineTransform":[1,0,0,1,0,0],"masksToBounds":false,"rotation":0,"scale":1,"position":{"pointX":480,"pointY":39.863967895507812},"width":966,"sublayerTransform":[1,0,0,0,0,1,0,0,0,0,1,0,0,0,0,1],"contentsRect":{"y":0,"x":0,"width":1,"height":1},"opacity":1,"edgeAntialiasingMask":0,"height":86,"hidden":true,"anchorPoint":{"pointX":0.5,"pointY":0.5}},"texture":"75BD6FF36F5358FE23CA21DC0E2B2B59"}]}]}]}},{"effects":[{"beginTime":0,"baseLayer":{"animations":[],"initialState":{"affineTransform":[1,0,0,1,0,0],"masksToBounds":false,"rotation":0,"scale":1,"position":{"pointX":515,"pointY":277.13603210449219},"width":966,"sublayerTransform":[1,0,0,0,0,1,0,0,0,0,1,0,0,0,0,1],"contentsRect":{"y":0,"x":0,"width":1,"height":1},"opacity":1,"edgeAntialiasingMask":251658240,"height":86,"hidden":false,"anchorPoint":{"pointX":0.5,"pointY":0.5}},"objectID":"98B8DDAD-86E4-4739-A0DA-7C1153DB4A89","layers":[{"animations":[],"initialState":{"affineTransform":[1,0,0,1,0,0],"masksToBounds":false,"rotation":0,"scale":1,"position":{"pointX":480,"pointY":149.86396789550781},"width":966,"sublayerTransform":[1,0,0,0,0,1,0,0,0,0,1,-0.00049229876906403734,0,0,0,1],"contentsRect":{"y":0,"x":0,"width":1,"height":1},"opacity":1,"edgeAntialiasingMask":251658240,"height":86,"hidden":false,"anchorPoint":{"pointX":0.49689440993788819,"pointY":1.7426042778547419}},"layers":[{"animations":[{"additive":false,"timeOffset":0,"beginTime":1e-100,"repeatCount":0,"fillMode":"both","duration":0.001,"autoreverses":false,"animations":[{"additive":false,"timeOffset":0,"beginTime":0,"from":{"scalar":true},"repeatCount":0,"fillMode":"both","duration":0.0001,"autoreverses":false,"property":"hidden","to":{"scalar":false},"removedOnCompletion":true},{"additive":false,"timeOffset":0,"beginTime":0.0001,"from":{"scalar":false},"repeatCount":0,"fillMode":"forwards","duration":0.00089999999999999998,"autoreverses":false,"property":"hidden","to":{"scalar":false},"removedOnCompletion":true}],"removedOnCompletion":false}],"layers":[],"texturedRectangle":{"isBackgroundTexture":true,"singleTextureOpacity":1,"textureType":5,"textBaseline":0,"textXHeight":0,"isVerticalText":false},"initialState":{"affineTransform":[1,0,0,1,0,0],"masksToBounds":false,"rotation":0,"scale":1,"position":{"pointX":480,"pointY":39.863967895507812},"width":966,"sublayerTransform":[1,0,0,0,0,1,0,0,0,0,1,0,0,0,0,1],"contentsRect":{"y":0,"x":0,"width":1,"height":1},"opacity":1,"edgeAntialiasingMask":0,"height":86,"hidden":true,"anchorPoint":{"pointX":0.5,"pointY":0.5}},"texture":"75BD6FF36F5358FE23CA21DC0E2B2B59"}]}]},"effects":[],"duration":0.001,"type":"buildIn","attributes":{"direction":0},"name":"apple:appear","objectID":"98B8DDAD-86E4-4739-A0DA-7C1153DB4A89"}],"automaticPlay":false,"hyperlinks":[],"accessibility":[{"text":"equation.pdf","targetRectangle":{"y":460.93682861328125,"x":346.1990309553442,"width":20.787277030323764,"height":33.316556337194697}},{"text":"Given a Markov kernel ￼ can construct a chain ￼ by iterating over ￼","targetRectangle":{"y":354.33309936523438,"x":61.654824018478394,"width":707.51718353084277,"height":33.373817505419026}},{"text":"equation.pdf","targetRectangle":{"y":511.54714965820312,"x":348.41738891601562,"width":282.74505945299848,"height":25.38674860604101}},{"text":"The marginal law ￼ of ￼ after ￼ steps satisfies","targetRectangle":{"y":460.93682861328125,"x":131.65482401847839,"width":435.89900733167542,"height":33.316556337194697}},{"text":"equation.pdf","targetRectangle":{"y":195.43658447265625,"x":291.46875,"width":404.70209024355131,"height":23.811000000000007}},{"text":"equation.pdf","targetRectangle":{"y":408.95050048828125,"x":412.14752197265625,"width":163.77309745094021,"height":23.520248598083867}},{"text":"￼","targetRectangle":{"y":66.408382415771484,"x":964.57660043239594,"width":23.0390625,"height":28}},{"text":"Given a Markov chain defines a Markov kernel as the one step transition","targetRectangle":{"y":238.13603210449219,"x":97.764708280563354,"width":679.18399999999974,"height":26.361846923828125}},{"text":"equation.pdf","targetRectangle":{"y":460.93682861328125,"x":297.53482401847839,"width":18.502206936865832,"height":33.316556337194697}},{"text":"equation.pdf","targetRectangle":{"y":291.52666219037121,"x":280.09764494433477,"width":425.71490623288685,"height":23.810999999999979}},{"text":"Markov kernels v4: Markov chains","targetRectangle":{"y":56.908382415771484,"x":36,"width":578.44800000000009,"height":48.400146484375}},{"text":"equation.pdf","targetRectangle":{"y":634.04052734375,"x":296.219970703125,"width":436.3112914620815,"height":68.98475017285341}},{"text":"equation.pdf","targetRectangle":{"y":354.33309936523438,"x":696.35318048805425,"width":72.818827061266916,"height":33.373817505419026}},{"text":"equation.pdf","targetRectangle":{"y":354.33309936523438,"x":278.20082401847839,"width":17.931079439252358,"height":31.721952634437059}},{"text":"equation.pdf","targetRectangle":{"y":137.54168701171875,"x":623.94273072106353,"width":20.646280373831814,"height":31.721952634437059}},{"text":"equation.pdf","targetRectangle":{"y":137.54168701171875,"x":219.40470828056334,"width":153.93602244050032,"height":33.373817505419026}},{"text":"The joint law of ￼ ","targetRectangle":{"y":577.320068359375,"x":133.87459063529968,"width":337.97634477694891,"height":33.37381750541897}},{"text":"A Markov Chain ￼ is a stochastic process in ￼ such that ","targetRectangle":{"y":137.54168701171875,"x":62.764708280563354,"width":682.05630281433173,"height":33.373817505419026}},{"text":"equation.pdf","targetRectangle":{"y":577.320068359375,"x":282.22059063529969,"width":183.51434477694892,"height":33.37381750541897}},{"text":"equation.pdf","targetRectangle":{"y":460.93682861328125,"x":421.19430798566793,"width":7.4735233644859704,"height":31.721952634437059}},{"text":"equation.pdf","targetRectangle":{"y":354.33309936523438,"x":512.54590345773079,"width":20.787277030323708,"height":33.316556337194697}}],"baseLayer":{"animations":[],"initialState":{"affineTransform":[1,0,0,1,0,0],"masksToBounds":false,"rotation":0,"scale":1,"position":{"pointX":512,"pointY":384},"width":1024,"sublayerTransform":[1,0,0,0,0,1,0,0,0,0,1,0,0,0,0,1],"contentsRect":{"y":0,"x":0,"width":1,"height":1},"opacity":1,"edgeAntialiasingMask":251658240,"height":768,"hidden":false,"anchorPoint":{"pointX":0.5,"pointY":0.5}},"layers":[{"animations":[],"initialState":{"affineTransform":[1,0,0,1,0,0],"masksToBounds":false,"rotation":0,"scale":1,"position":{"pointX":512,"pointY":384},"width":1024,"sublayerTransform":[1,0,0,0,0,1,0,0,0,0,1,0,0,0,0,1],"contentsRect":{"y":0,"x":0,"width":1,"height":1},"opacity":1,"edgeAntialiasingMask":251658240,"height":768,"hidden":false,"anchorPoint":{"pointX":0.5,"pointY":0.5}},"layers":[{"animations":[],"initialState":{"affineTransform":[1,0,0,1,0,0],"masksToBounds":false,"rotation":0,"scale":1,"position":{"pointX":512,"pointY":384},"width":1024,"sublayerTransform":[1,0,0,0,0,1,0,0,0,0,1,0,0,0,0,1],"contentsRect":{"y":0,"x":0,"width":1,"height":1},"opacity":1,"edgeAntialiasingMask":251658240,"height":768,"hidden":false,"anchorPoint":{"pointX":0.5,"pointY":0.5}},"layers":[{"animations":[],"layers":[],"texturedRectangle":{"isBackgroundTexture":true,"singleTextureOpacity":1,"textureType":1,"textBaseline":0,"textXHeight":0,"isVerticalText":false},"initialState":{"affineTransform":[1,0,0,1,0,0],"masksToBounds":false,"rotation":0,"scale":1,"position":{"pointX":512,"pointY":384},"width":1024,"sublayerTransform":[1,0,0,0,0,1,0,0,0,0,1,0,0,0,0,1],"contentsRect":{"y":0,"x":0,"width":1,"height":1},"opacity":1,"edgeAntialiasingMask":0,"height":768,"hidden":false,"anchorPoint":{"pointX":0.5,"pointY":0.5}},"texture":"9251636AE7EC24F2536617C9E7909BA3"}]}]},{"animations":[],"initialState":{"affineTransform":[1,0,0,1,0,0],"masksToBounds":false,"rotation":0,"scale":1,"position":{"pointX":512,"pointY":384},"width":1024,"sublayerTransform":[1,0,0,0,0,1,0,0,0,0,1,0,0,0,0,1],"contentsRect":{"y":0,"x":0,"width":1,"height":1},"opacity":1,"edgeAntialiasingMask":251658240,"height":768,"hidden":false,"anchorPoint":{"pointX":0.5,"pointY":0.5}},"layers":[{"animations":[],"initialState":{"affineTransform":[1,0,0,1,0,0],"masksToBounds":false,"rotation":0,"scale":1,"position":{"pointX":321,"pointY":71.908382415771484},"width":578,"sublayerTransform":[1,0,0,0,0,1,0,0,0,0,1,0,0,0,0,1],"contentsRect":{"y":0,"x":0,"width":1,"height":1},"opacity":1,"edgeAntialiasingMask":251658240,"height":38,"hidden":false,"anchorPoint":{"pointX":0.5,"pointY":0.5}},"layers":[{"animations":[],"layers":[],"texturedRectangle":{"singleTextureOpacity":1,"textXHeight":0.640421052631579,"textBaseline":0.96012627451043375,"isBackgroundTexture":true,"isVerticalText":false,"textColor":[0.46666663885116577,0.113725446164608,0.46274513006210327,1],"textureType":6},"initialState":{"affineTransform":[1,0,0,1,0,0],"masksToBounds":false,"rotation":0,"scale":1,"position":{"pointX":294,"pointY":21.091617584228516},"width":578,"sublayerTransform":[1,0,0,0,0,1,0,0,0,0,1,0,0,0,0,1],"contentsRect":{"y":0,"x":0,"width":1,"height":1},"opacity":1,"edgeAntialiasingMask":0,"height":38,"hidden":false,"anchorPoint":{"pointX":0.5,"pointY":0.5}},"texture":"58B928AAF0171AFA33A1A9DB076B54DF"}]}]},{"animations":[],"initialState":{"affineTransform":[1,0,0,1,0,0],"masksToBounds":false,"rotation":0,"scale":1,"position":{"pointX":512,"pointY":384},"width":1024,"sublayerTransform":[1,0,0,0,0,1,0,0,0,0,1,0,0,0,0,1],"contentsRect":{"y":0,"x":0,"width":1,"height":1},"opacity":1,"edgeAntialiasingMask":251658240,"height":768,"hidden":false,"anchorPoint":{"pointX":0.5,"pointY":0.5}},"layers":[{"animations":[],"initialState":{"affineTransform":[1,0,0,1,0,0],"masksToBounds":false,"rotation":0,"scale":1,"position":{"pointX":972.57660043239594,"pointY":72.908382415771484},"width":26,"sublayerTransform":[1,0,0,0,0,1,0,0,0,0,1,0,0,0,0,1],"contentsRect":{"y":0,"x":0,"width":1,"height":1},"opacity":1,"edgeAntialiasingMask":251658240,"height":21,"hidden":false,"anchorPoint":{"pointX":0.5,"pointY":0.5}},"layers":[{"animations":[],"layers":[],"texturedRectangle":{"singleTextureOpacity":1,"textXHeight":0.8203125,"textBaseline":0.90393338884626118,"isBackgroundTexture":true,"isVerticalText":false,"textColor":[0.65252363681793213,0.66733616590499878,0.66081041097640991,1],"textureType":6},"initialState":{"affineTransform":[1,0,0,1,0,0],"masksToBounds":false,"rotation":0,"scale":1,"position":{"pointX":16.423399567604065,"pointY":18.091617584228516},"width":26,"sublayerTransform":[1,0,0,0,0,1,0,0,0,0,1,0,0,0,0,1],"contentsRect":{"y":0,"x":0,"width":1,"height":1},"opacity":1,"edgeAntialiasingMask":0,"height":21,"hidden":false,"anchorPoint":{"pointX":0.5,"pointY":0.5}},"texture":"95D7342E436EC3FA033869266AFFF539"}]}]},{"animations":[],"initialState":{"affineTransform":[1,0,0,1,0,0],"masksToBounds":false,"rotation":0,"scale":1,"position":{"pointX":512,"pointY":384},"width":1024,"sublayerTransform":[1,0,0,0,0,1,0,0,0,0,1,0,0,0,0,1],"contentsRect":{"y":0,"x":0,"width":1,"height":1},"opacity":1,"edgeAntialiasingMask":251658240,"height":768,"hidden":false,"anchorPoint":{"pointX":0.5,"pointY":0.5}},"layers":[{"animations":[],"initialState":{"affineTransform":[1,0,0,1,0,0],"masksToBounds":false,"rotation":0,"scale":1,"position":{"pointX":516,"pointY":179.04168701171875},"width":968,"sublayerTransform":[1,0,0,0,0,1,0,0,0,0,1,0,0,0,0,1],"contentsRect":{"y":0,"x":0,"width":1,"height":1},"opacity":1,"edgeAntialiasingMask":251658240,"height":91,"hidden":false,"anchorPoint":{"pointX":0.5,"pointY":0.5}},"objectID":"8EB51A19-E110-4214-8053-342AEA12F7AC","layers":[{"animations":[],"layers":[],"texturedRectangle":{"isBackgroundTexture":true,"singleTextureOpacity":1,"textureType":5,"textBaseline":0,"textXHeight":0,"isVerticalText":false},"initialState":{"affineTransform":[1,0,0,1,0,0],"masksToBounds":false,"rotation":0,"scale":1,"position":{"pointX":480,"pointY":41.95831298828125},"width":968,"sublayerTransform":[1,0,0,0,0,1,0,0,0,0,1,0,0,0,0,1],"contentsRect":{"y":0,"x":0,"width":1,"height":1},"opacity":1,"edgeAntialiasingMask":0,"height":91,"hidden":false,"anchorPoint":{"pointX":0.5,"pointY":0.5}},"texture":"DC9A3BA08A4D9EB735DA96258A475113"}]}]},{"animations":[],"initialState":{"affineTransform":[1,0,0,1,0,0],"masksToBounds":false,"rotation":0,"scale":1,"position":{"pointX":512,"pointY":384},"width":1024,"sublayerTransform":[1,0,0,0,0,1,0,0,0,0,1,0,0,0,0,1],"contentsRect":{"y":0,"x":0,"width":1,"height":1},"opacity":1,"edgeAntialiasingMask":251658240,"height":768,"hidden":false,"anchorPoint":{"pointX":0.5,"pointY":0.5}},"layers":[{"animations":[],"initialState":{"affineTransform":[1,0,0,1,0,0],"masksToBounds":false,"rotation":0,"scale":1,"position":{"pointX":514.89011573791504,"pointY":393.83309936523438},"width":968,"sublayerTransform":[1,0,0,0,0,1,0,0,0,0,1,0,0,0,0,1],"contentsRect":{"y":0,"x":0,"width":1,"height":1},"opacity":1,"edgeAntialiasingMask":251658240,"height":87,"hidden":false,"anchorPoint":{"pointX":0.5,"pointY":0.5}},"objectID":"6E97E328-7C58-4ECD-BD54-4E2DE3E7B534","layers":[{"animations":[],"layers":[],"texturedRectangle":{"isBackgroundTexture":true,"singleTextureOpacity":1,"textureType":5,"textBaseline":0,"textXHeight":0,"isVerticalText":false},"initialState":{"affineTransform":[1,0,0,1,0,0],"masksToBounds":false,"rotation":0,"scale":1,"position":{"pointX":480.10988426208496,"pointY":40.166900634765625},"width":968,"sublayerTransform":[1,0,0,0,0,1,0,0,0,0,1,0,0,0,0,1],"contentsRect":{"y":0,"x":0,"width":1,"height":1},"opacity":1,"edgeAntialiasingMask":0,"height":87,"hidden":true,"anchorPoint":{"pointX":0.5,"pointY":0.5}},"texture":"BF223A31E7255648FF4367CA0B6DC93E"}]}]},{"animations":[],"initialState":{"affineTransform":[1,0,0,1,0,0],"masksToBounds":false,"rotation":0,"scale":1,"position":{"pointX":512,"pointY":384},"width":1024,"sublayerTransform":[1,0,0,0,0,1,0,0,0,0,1,0,0,0,0,1],"contentsRect":{"y":0,"x":0,"width":1,"height":1},"opacity":1,"edgeAntialiasingMask":251658240,"height":768,"hidden":false,"anchorPoint":{"pointX":0.5,"pointY":0.5}},"layers":[{"animations":[],"initialState":{"affineTransform":[1,0,0,1,0,0],"masksToBounds":false,"rotation":0,"scale":1,"position":{"pointX":514.89011573791504,"pointY":499.43682861328125},"width":968,"sublayerTransform":[1,0,0,0,0,1,0,0,0,0,1,0,0,0,0,1],"contentsRect":{"y":0,"x":0,"width":1,"height":1},"opacity":1,"edgeAntialiasingMask":251658240,"height":85,"hidden":false,"anchorPoint":{"pointX":0.5,"pointY":0.5}},"objectID":"2D2998DE-7084-4730-A789-BB46D87301FC","layers":[{"animations":[],"layers":[],"texturedRectangle":{"isBackgroundTexture":true,"singleTextureOpacity":1,"textureType":5,"textBaseline":0,"textXHeight":0,"isVerticalText":false},"initialState":{"affineTransform":[1,0,0,1,0,0],"masksToBounds":false,"rotation":0,"scale":1,"position":{"pointX":480.10988426208496,"pointY":38.56317138671875},"width":968,"sublayerTransform":[1,0,0,0,0,1,0,0,0,0,1,0,0,0,0,1],"contentsRect":{"y":0,"x":0,"width":1,"height":1},"opacity":1,"edgeAntialiasingMask":0,"height":85,"hidden":true,"anchorPoint":{"pointX":0.5,"pointY":0.5}},"texture":"2AC635A1B91F79381B7DC140DF8EC6FD"}]}]},{"animations":[],"initialState":{"affineTransform":[1,0,0,1,0,0],"masksToBounds":false,"rotation":0,"scale":1,"position":{"pointX":512,"pointY":384},"width":1024,"sublayerTransform":[1,0,0,0,0,1,0,0,0,0,1,0,0,0,0,1],"contentsRect":{"y":0,"x":0,"width":1,"height":1},"opacity":1,"edgeAntialiasingMask":251658240,"height":768,"hidden":false,"anchorPoint":{"pointX":0.5,"pointY":0.5}},"layers":[{"animations":[],"initialState":{"affineTransform":[1,0,0,1,0,0],"masksToBounds":false,"rotation":0,"scale":1,"position":{"pointX":517.10988235473633,"pointY":640.820068359375},"width":968,"sublayerTransform":[1,0,0,0,0,1,0,0,0,0,1,0,0,0,0,1],"contentsRect":{"y":0,"x":0,"width":1,"height":1},"opacity":1,"edgeAntialiasingMask":251658240,"height":135,"hidden":false,"anchorPoint":{"pointX":0.5,"pointY":0.5}},"objectID":"32BD2261-3E37-460F-B23A-521CCBCDB33F","layers":[{"animations":[],"layers":[],"texturedRectangle":{"isBackgroundTexture":true,"singleTextureOpacity":1,"textureType":5,"textBaseline":0,"textXHeight":0,"isVerticalText":false},"initialState":{"affineTransform":[1,0,0,1,0,0],"masksToBounds":false,"rotation":0,"scale":1,"position":{"pointX":479.89011764526367,"pointY":64.179931640625},"width":968,"sublayerTransform":[1,0,0,0,0,1,0,0,0,0,1,0,0,0,0,1],"contentsRect":{"y":0,"x":0,"width":1,"height":1},"opacity":1,"edgeAntialiasingMask":0,"height":135,"hidden":true,"anchorPoint":{"pointX":0.5,"pointY":0.5}},"texture":"51362B679AAC4739143AF2ABA5836914"}]}]},{"animations":[],"initialState":{"affineTransform":[1,0,0,1,0,0],"masksToBounds":false,"rotation":0,"scale":1,"position":{"pointX":512,"pointY":384},"width":1024,"sublayerTransform":[1,0,0,0,0,1,0,0,0,0,1,0,0,0,0,1],"contentsRect":{"y":0,"x":0,"width":1,"height":1},"opacity":1,"edgeAntialiasingMask":251658240,"height":768,"hidden":false,"anchorPoint":{"pointX":0.5,"pointY":0.5}},"layers":[{"animations":[],"initialState":{"affineTransform":[1,0,0,1,0,0],"masksToBounds":false,"rotation":0,"scale":1,"position":{"pointX":515,"pointY":277.13603210449219},"width":966,"sublayerTransform":[1,0,0,0,0,1,0,0,0,0,1,0,0,0,0,1],"contentsRect":{"y":0,"x":0,"width":1,"height":1},"opacity":1,"edgeAntialiasingMask":251658240,"height":86,"hidden":false,"anchorPoint":{"pointX":0.5,"pointY":0.5}},"objectID":"98B8DDAD-86E4-4739-A0DA-7C1153DB4A89","layers":[{"animations":[],"layers":[],"texturedRectangle":{"isBackgroundTexture":true,"singleTextureOpacity":1,"textureType":5,"textBaseline":0,"textXHeight":0,"isVerticalText":false},"initialState":{"affineTransform":[1,0,0,1,0,0],"masksToBounds":false,"rotation":0,"scale":1,"position":{"pointX":480,"pointY":39.863967895507812},"width":966,"sublayerTransform":[1,0,0,0,0,1,0,0,0,0,1,0,0,0,0,1],"contentsRect":{"y":0,"x":0,"width":1,"height":1},"opacity":1,"edgeAntialiasingMask":0,"height":86,"hidden":true,"anchorPoint":{"pointX":0.5,"pointY":0.5}},"texture":"75BD6FF36F5358FE23CA21DC0E2B2B59"}]}]}]}},{"effects":[{"beginTime":0,"baseLayer":{"animations":[],"initialState":{"affineTransform":[1,0,0,1,0,0],"masksToBounds":false,"rotation":0,"scale":1,"position":{"pointX":514.89011573791504,"pointY":393.83309936523438},"width":968,"sublayerTransform":[1,0,0,0,0,1,0,0,0,0,1,0,0,0,0,1],"contentsRect":{"y":0,"x":0,"width":1,"height":1},"opacity":1,"edgeAntialiasingMask":251658240,"height":87,"hidden":false,"anchorPoint":{"pointX":0.5,"pointY":0.5}},"objectID":"6E97E328-7C58-4ECD-BD54-4E2DE3E7B534","layers":[{"animations":[],"initialState":{"affineTransform":[1,0,0,1,0,0],"masksToBounds":false,"rotation":0,"scale":1,"position":{"pointX":481.10988426208496,"pointY":33.666900634765625},"width":968,"sublayerTransform":[1,0,0,0,0,1,0,0,0,0,1,-0.00049229876906403734,0,0,0,1],"contentsRect":{"y":0,"x":0,"width":1,"height":1},"opacity":1,"edgeAntialiasingMask":251658240,"height":87,"hidden":false,"anchorPoint":{"pointX":0.49701434324595556,"pointY":0.38697586936512213}},"layers":[{"animations":[{"additive":false,"timeOffset":0,"beginTime":1e-100,"repeatCount":0,"fillMode":"both","duration":0.001,"autoreverses":false,"animations":[{"additive":false,"timeOffset":0,"beginTime":0,"from":{"scalar":true},"repeatCount":0,"fillMode":"both","duration":0.0001,"autoreverses":false,"property":"hidden","to":{"scalar":false},"removedOnCompletion":true},{"additive":false,"timeOffset":0,"beginTime":0.0001,"from":{"scalar":false},"repeatCount":0,"fillMode":"forwards","duration":0.00089999999999999998,"autoreverses":false,"property":"hidden","to":{"scalar":false},"removedOnCompletion":true}],"removedOnCompletion":false}],"layers":[],"texturedRectangle":{"isBackgroundTexture":true,"singleTextureOpacity":1,"textureType":5,"textBaseline":0,"textXHeight":0,"isVerticalText":false},"initialState":{"affineTransform":[1,0,0,1,0,0],"masksToBounds":false,"rotation":0,"scale":1,"position":{"pointX":480.10988426208496,"pointY":40.166900634765625},"width":968,"sublayerTransform":[1,0,0,0,0,1,0,0,0,0,1,0,0,0,0,1],"contentsRect":{"y":0,"x":0,"width":1,"height":1},"opacity":1,"edgeAntialiasingMask":0,"height":87,"hidden":true,"anchorPoint":{"pointX":0.5,"pointY":0.5}},"texture":"BF223A31E7255648FF4367CA0B6DC93E"}]}]},"effects":[],"duration":0.001,"type":"buildIn","attributes":{"direction":0},"name":"apple:appear","objectID":"6E97E328-7C58-4ECD-BD54-4E2DE3E7B534"}],"automaticPlay":false,"hyperlinks":[],"accessibility":[{"text":"equation.pdf","targetRectangle":{"y":460.93682861328125,"x":346.1990309553442,"width":20.787277030323764,"height":33.316556337194697}},{"text":"Given a Markov kernel ￼ can construct a chain ￼ by iterating over ￼","targetRectangle":{"y":354.33309936523438,"x":61.654824018478394,"width":707.51718353084277,"height":33.373817505419026}},{"text":"equation.pdf","targetRectangle":{"y":511.54714965820312,"x":348.41738891601562,"width":282.74505945299848,"height":25.38674860604101}},{"text":"The marginal law ￼ of ￼ after ￼ steps satisfies","targetRectangle":{"y":460.93682861328125,"x":131.65482401847839,"width":435.89900733167542,"height":33.316556337194697}},{"text":"equation.pdf","targetRectangle":{"y":195.43658447265625,"x":291.46875,"width":404.70209024355131,"height":23.811000000000007}},{"text":"equation.pdf","targetRectangle":{"y":408.95050048828125,"x":412.14752197265625,"width":163.77309745094021,"height":23.520248598083867}},{"text":"￼","targetRectangle":{"y":66.408382415771484,"x":964.57660043239594,"width":23.0390625,"height":28}},{"text":"Given a Markov chain defines a Markov kernel as the one step transition","targetRectangle":{"y":238.13603210449219,"x":97.764708280563354,"width":679.18399999999974,"height":26.361846923828125}},{"text":"equation.pdf","targetRectangle":{"y":460.93682861328125,"x":297.53482401847839,"width":18.502206936865832,"height":33.316556337194697}},{"text":"equation.pdf","targetRectangle":{"y":291.52666219037121,"x":280.09764494433477,"width":425.71490623288685,"height":23.810999999999979}},{"text":"Markov kernels v4: Markov chains","targetRectangle":{"y":56.908382415771484,"x":36,"width":578.44800000000009,"height":48.400146484375}},{"text":"equation.pdf","targetRectangle":{"y":634.04052734375,"x":296.219970703125,"width":436.3112914620815,"height":68.98475017285341}},{"text":"equation.pdf","targetRectangle":{"y":354.33309936523438,"x":696.35318048805425,"width":72.818827061266916,"height":33.373817505419026}},{"text":"equation.pdf","targetRectangle":{"y":354.33309936523438,"x":278.20082401847839,"width":17.931079439252358,"height":31.721952634437059}},{"text":"equation.pdf","targetRectangle":{"y":137.54168701171875,"x":623.94273072106353,"width":20.646280373831814,"height":31.721952634437059}},{"text":"equation.pdf","targetRectangle":{"y":137.54168701171875,"x":219.40470828056334,"width":153.93602244050032,"height":33.373817505419026}},{"text":"The joint law of ￼ ","targetRectangle":{"y":577.320068359375,"x":133.87459063529968,"width":337.97634477694891,"height":33.37381750541897}},{"text":"A Markov Chain ￼ is a stochastic process in ￼ such that ","targetRectangle":{"y":137.54168701171875,"x":62.764708280563354,"width":682.05630281433173,"height":33.373817505419026}},{"text":"equation.pdf","targetRectangle":{"y":577.320068359375,"x":282.22059063529969,"width":183.51434477694892,"height":33.37381750541897}},{"text":"equation.pdf","targetRectangle":{"y":460.93682861328125,"x":421.19430798566793,"width":7.4735233644859704,"height":31.721952634437059}},{"text":"equation.pdf","targetRectangle":{"y":354.33309936523438,"x":512.54590345773079,"width":20.787277030323708,"height":33.316556337194697}}],"baseLayer":{"animations":[],"initialState":{"affineTransform":[1,0,0,1,0,0],"masksToBounds":false,"rotation":0,"scale":1,"position":{"pointX":512,"pointY":384},"width":1024,"sublayerTransform":[1,0,0,0,0,1,0,0,0,0,1,0,0,0,0,1],"contentsRect":{"y":0,"x":0,"width":1,"height":1},"opacity":1,"edgeAntialiasingMask":251658240,"height":768,"hidden":false,"anchorPoint":{"pointX":0.5,"pointY":0.5}},"layers":[{"animations":[],"initialState":{"affineTransform":[1,0,0,1,0,0],"masksToBounds":false,"rotation":0,"scale":1,"position":{"pointX":512,"pointY":384},"width":1024,"sublayerTransform":[1,0,0,0,0,1,0,0,0,0,1,0,0,0,0,1],"contentsRect":{"y":0,"x":0,"width":1,"height":1},"opacity":1,"edgeAntialiasingMask":251658240,"height":768,"hidden":false,"anchorPoint":{"pointX":0.5,"pointY":0.5}},"layers":[{"animations":[],"initialState":{"affineTransform":[1,0,0,1,0,0],"masksToBounds":false,"rotation":0,"scale":1,"position":{"pointX":512,"pointY":384},"width":1024,"sublayerTransform":[1,0,0,0,0,1,0,0,0,0,1,0,0,0,0,1],"contentsRect":{"y":0,"x":0,"width":1,"height":1},"opacity":1,"edgeAntialiasingMask":251658240,"height":768,"hidden":false,"anchorPoint":{"pointX":0.5,"pointY":0.5}},"layers":[{"animations":[],"layers":[],"texturedRectangle":{"isBackgroundTexture":true,"singleTextureOpacity":1,"textureType":1,"textBaseline":0,"textXHeight":0,"isVerticalText":false},"initialState":{"affineTransform":[1,0,0,1,0,0],"masksToBounds":false,"rotation":0,"scale":1,"position":{"pointX":512,"pointY":384},"width":1024,"sublayerTransform":[1,0,0,0,0,1,0,0,0,0,1,0,0,0,0,1],"contentsRect":{"y":0,"x":0,"width":1,"height":1},"opacity":1,"edgeAntialiasingMask":0,"height":768,"hidden":false,"anchorPoint":{"pointX":0.5,"pointY":0.5}},"texture":"9251636AE7EC24F2536617C9E7909BA3"}]}]},{"animations":[],"initialState":{"affineTransform":[1,0,0,1,0,0],"masksToBounds":false,"rotation":0,"scale":1,"position":{"pointX":512,"pointY":384},"width":1024,"sublayerTransform":[1,0,0,0,0,1,0,0,0,0,1,0,0,0,0,1],"contentsRect":{"y":0,"x":0,"width":1,"height":1},"opacity":1,"edgeAntialiasingMask":251658240,"height":768,"hidden":false,"anchorPoint":{"pointX":0.5,"pointY":0.5}},"layers":[{"animations":[],"initialState":{"affineTransform":[1,0,0,1,0,0],"masksToBounds":false,"rotation":0,"scale":1,"position":{"pointX":321,"pointY":71.908382415771484},"width":578,"sublayerTransform":[1,0,0,0,0,1,0,0,0,0,1,0,0,0,0,1],"contentsRect":{"y":0,"x":0,"width":1,"height":1},"opacity":1,"edgeAntialiasingMask":251658240,"height":38,"hidden":false,"anchorPoint":{"pointX":0.5,"pointY":0.5}},"layers":[{"animations":[],"layers":[],"texturedRectangle":{"singleTextureOpacity":1,"textXHeight":0.640421052631579,"textBaseline":0.96012627451043375,"isBackgroundTexture":true,"isVerticalText":false,"textColor":[0.46666663885116577,0.113725446164608,0.46274513006210327,1],"textureType":6},"initialState":{"affineTransform":[1,0,0,1,0,0],"masksToBounds":false,"rotation":0,"scale":1,"position":{"pointX":294,"pointY":21.091617584228516},"width":578,"sublayerTransform":[1,0,0,0,0,1,0,0,0,0,1,0,0,0,0,1],"contentsRect":{"y":0,"x":0,"width":1,"height":1},"opacity":1,"edgeAntialiasingMask":0,"height":38,"hidden":false,"anchorPoint":{"pointX":0.5,"pointY":0.5}},"texture":"58B928AAF0171AFA33A1A9DB076B54DF"}]}]},{"animations":[],"initialState":{"affineTransform":[1,0,0,1,0,0],"masksToBounds":false,"rotation":0,"scale":1,"position":{"pointX":512,"pointY":384},"width":1024,"sublayerTransform":[1,0,0,0,0,1,0,0,0,0,1,0,0,0,0,1],"contentsRect":{"y":0,"x":0,"width":1,"height":1},"opacity":1,"edgeAntialiasingMask":251658240,"height":768,"hidden":false,"anchorPoint":{"pointX":0.5,"pointY":0.5}},"layers":[{"animations":[],"initialState":{"affineTransform":[1,0,0,1,0,0],"masksToBounds":false,"rotation":0,"scale":1,"position":{"pointX":972.57660043239594,"pointY":72.908382415771484},"width":26,"sublayerTransform":[1,0,0,0,0,1,0,0,0,0,1,0,0,0,0,1],"contentsRect":{"y":0,"x":0,"width":1,"height":1},"opacity":1,"edgeAntialiasingMask":251658240,"height":21,"hidden":false,"anchorPoint":{"pointX":0.5,"pointY":0.5}},"layers":[{"animations":[],"layers":[],"texturedRectangle":{"singleTextureOpacity":1,"textXHeight":0.8203125,"textBaseline":0.90393338884626118,"isBackgroundTexture":true,"isVerticalText":false,"textColor":[0.65252363681793213,0.66733616590499878,0.66081041097640991,1],"textureType":6},"initialState":{"affineTransform":[1,0,0,1,0,0],"masksToBounds":false,"rotation":0,"scale":1,"position":{"pointX":16.423399567604065,"pointY":18.091617584228516},"width":26,"sublayerTransform":[1,0,0,0,0,1,0,0,0,0,1,0,0,0,0,1],"contentsRect":{"y":0,"x":0,"width":1,"height":1},"opacity":1,"edgeAntialiasingMask":0,"height":21,"hidden":false,"anchorPoint":{"pointX":0.5,"pointY":0.5}},"texture":"95D7342E436EC3FA033869266AFFF539"}]}]},{"animations":[],"initialState":{"affineTransform":[1,0,0,1,0,0],"masksToBounds":false,"rotation":0,"scale":1,"position":{"pointX":512,"pointY":384},"width":1024,"sublayerTransform":[1,0,0,0,0,1,0,0,0,0,1,0,0,0,0,1],"contentsRect":{"y":0,"x":0,"width":1,"height":1},"opacity":1,"edgeAntialiasingMask":251658240,"height":768,"hidden":false,"anchorPoint":{"pointX":0.5,"pointY":0.5}},"layers":[{"animations":[],"initialState":{"affineTransform":[1,0,0,1,0,0],"masksToBounds":false,"rotation":0,"scale":1,"position":{"pointX":516,"pointY":179.04168701171875},"width":968,"sublayerTransform":[1,0,0,0,0,1,0,0,0,0,1,0,0,0,0,1],"contentsRect":{"y":0,"x":0,"width":1,"height":1},"opacity":1,"edgeAntialiasingMask":251658240,"height":91,"hidden":false,"anchorPoint":{"pointX":0.5,"pointY":0.5}},"objectID":"8EB51A19-E110-4214-8053-342AEA12F7AC","layers":[{"animations":[],"layers":[],"texturedRectangle":{"isBackgroundTexture":true,"singleTextureOpacity":1,"textureType":5,"textBaseline":0,"textXHeight":0,"isVerticalText":false},"initialState":{"affineTransform":[1,0,0,1,0,0],"masksToBounds":false,"rotation":0,"scale":1,"position":{"pointX":480,"pointY":41.95831298828125},"width":968,"sublayerTransform":[1,0,0,0,0,1,0,0,0,0,1,0,0,0,0,1],"contentsRect":{"y":0,"x":0,"width":1,"height":1},"opacity":1,"edgeAntialiasingMask":0,"height":91,"hidden":false,"anchorPoint":{"pointX":0.5,"pointY":0.5}},"texture":"DC9A3BA08A4D9EB735DA96258A475113"}]}]},{"animations":[],"initialState":{"affineTransform":[1,0,0,1,0,0],"masksToBounds":false,"rotation":0,"scale":1,"position":{"pointX":512,"pointY":384},"width":1024,"sublayerTransform":[1,0,0,0,0,1,0,0,0,0,1,0,0,0,0,1],"contentsRect":{"y":0,"x":0,"width":1,"height":1},"opacity":1,"edgeAntialiasingMask":251658240,"height":768,"hidden":false,"anchorPoint":{"pointX":0.5,"pointY":0.5}},"layers":[{"animations":[],"initialState":{"affineTransform":[1,0,0,1,0,0],"masksToBounds":false,"rotation":0,"scale":1,"position":{"pointX":514.89011573791504,"pointY":393.83309936523438},"width":968,"sublayerTransform":[1,0,0,0,0,1,0,0,0,0,1,0,0,0,0,1],"contentsRect":{"y":0,"x":0,"width":1,"height":1},"opacity":1,"edgeAntialiasingMask":251658240,"height":87,"hidden":false,"anchorPoint":{"pointX":0.5,"pointY":0.5}},"objectID":"6E97E328-7C58-4ECD-BD54-4E2DE3E7B534","layers":[{"animations":[],"layers":[],"texturedRectangle":{"isBackgroundTexture":true,"singleTextureOpacity":1,"textureType":5,"textBaseline":0,"textXHeight":0,"isVerticalText":false},"initialState":{"affineTransform":[1,0,0,1,0,0],"masksToBounds":false,"rotation":0,"scale":1,"position":{"pointX":480.10988426208496,"pointY":40.166900634765625},"width":968,"sublayerTransform":[1,0,0,0,0,1,0,0,0,0,1,0,0,0,0,1],"contentsRect":{"y":0,"x":0,"width":1,"height":1},"opacity":1,"edgeAntialiasingMask":0,"height":87,"hidden":true,"anchorPoint":{"pointX":0.5,"pointY":0.5}},"texture":"BF223A31E7255648FF4367CA0B6DC93E"}]}]},{"animations":[],"initialState":{"affineTransform":[1,0,0,1,0,0],"masksToBounds":false,"rotation":0,"scale":1,"position":{"pointX":512,"pointY":384},"width":1024,"sublayerTransform":[1,0,0,0,0,1,0,0,0,0,1,0,0,0,0,1],"contentsRect":{"y":0,"x":0,"width":1,"height":1},"opacity":1,"edgeAntialiasingMask":251658240,"height":768,"hidden":false,"anchorPoint":{"pointX":0.5,"pointY":0.5}},"layers":[{"animations":[],"initialState":{"affineTransform":[1,0,0,1,0,0],"masksToBounds":false,"rotation":0,"scale":1,"position":{"pointX":514.89011573791504,"pointY":499.43682861328125},"width":968,"sublayerTransform":[1,0,0,0,0,1,0,0,0,0,1,0,0,0,0,1],"contentsRect":{"y":0,"x":0,"width":1,"height":1},"opacity":1,"edgeAntialiasingMask":251658240,"height":85,"hidden":false,"anchorPoint":{"pointX":0.5,"pointY":0.5}},"objectID":"2D2998DE-7084-4730-A789-BB46D87301FC","layers":[{"animations":[],"layers":[],"texturedRectangle":{"isBackgroundTexture":true,"singleTextureOpacity":1,"textureType":5,"textBaseline":0,"textXHeight":0,"isVerticalText":false},"initialState":{"affineTransform":[1,0,0,1,0,0],"masksToBounds":false,"rotation":0,"scale":1,"position":{"pointX":480.10988426208496,"pointY":38.56317138671875},"width":968,"sublayerTransform":[1,0,0,0,0,1,0,0,0,0,1,0,0,0,0,1],"contentsRect":{"y":0,"x":0,"width":1,"height":1},"opacity":1,"edgeAntialiasingMask":0,"height":85,"hidden":true,"anchorPoint":{"pointX":0.5,"pointY":0.5}},"texture":"2AC635A1B91F79381B7DC140DF8EC6FD"}]}]},{"animations":[],"initialState":{"affineTransform":[1,0,0,1,0,0],"masksToBounds":false,"rotation":0,"scale":1,"position":{"pointX":512,"pointY":384},"width":1024,"sublayerTransform":[1,0,0,0,0,1,0,0,0,0,1,0,0,0,0,1],"contentsRect":{"y":0,"x":0,"width":1,"height":1},"opacity":1,"edgeAntialiasingMask":251658240,"height":768,"hidden":false,"anchorPoint":{"pointX":0.5,"pointY":0.5}},"layers":[{"animations":[],"initialState":{"affineTransform":[1,0,0,1,0,0],"masksToBounds":false,"rotation":0,"scale":1,"position":{"pointX":517.10988235473633,"pointY":640.820068359375},"width":968,"sublayerTransform":[1,0,0,0,0,1,0,0,0,0,1,0,0,0,0,1],"contentsRect":{"y":0,"x":0,"width":1,"height":1},"opacity":1,"edgeAntialiasingMask":251658240,"height":135,"hidden":false,"anchorPoint":{"pointX":0.5,"pointY":0.5}},"objectID":"32BD2261-3E37-460F-B23A-521CCBCDB33F","layers":[{"animations":[],"layers":[],"texturedRectangle":{"isBackgroundTexture":true,"singleTextureOpacity":1,"textureType":5,"textBaseline":0,"textXHeight":0,"isVerticalText":false},"initialState":{"affineTransform":[1,0,0,1,0,0],"masksToBounds":false,"rotation":0,"scale":1,"position":{"pointX":479.89011764526367,"pointY":64.179931640625},"width":968,"sublayerTransform":[1,0,0,0,0,1,0,0,0,0,1,0,0,0,0,1],"contentsRect":{"y":0,"x":0,"width":1,"height":1},"opacity":1,"edgeAntialiasingMask":0,"height":135,"hidden":true,"anchorPoint":{"pointX":0.5,"pointY":0.5}},"texture":"51362B679AAC4739143AF2ABA5836914"}]}]},{"animations":[],"initialState":{"affineTransform":[1,0,0,1,0,0],"masksToBounds":false,"rotation":0,"scale":1,"position":{"pointX":512,"pointY":384},"width":1024,"sublayerTransform":[1,0,0,0,0,1,0,0,0,0,1,0,0,0,0,1],"contentsRect":{"y":0,"x":0,"width":1,"height":1},"opacity":1,"edgeAntialiasingMask":251658240,"height":768,"hidden":false,"anchorPoint":{"pointX":0.5,"pointY":0.5}},"layers":[{"animations":[],"initialState":{"affineTransform":[1,0,0,1,0,0],"masksToBounds":false,"rotation":0,"scale":1,"position":{"pointX":515,"pointY":277.13603210449219},"width":966,"sublayerTransform":[1,0,0,0,0,1,0,0,0,0,1,0,0,0,0,1],"contentsRect":{"y":0,"x":0,"width":1,"height":1},"opacity":1,"edgeAntialiasingMask":251658240,"height":86,"hidden":false,"anchorPoint":{"pointX":0.5,"pointY":0.5}},"objectID":"98B8DDAD-86E4-4739-A0DA-7C1153DB4A89","layers":[{"animations":[],"layers":[],"texturedRectangle":{"isBackgroundTexture":true,"singleTextureOpacity":1,"textureType":5,"textBaseline":0,"textXHeight":0,"isVerticalText":false},"initialState":{"affineTransform":[1,0,0,1,0,0],"masksToBounds":false,"rotation":0,"scale":1,"position":{"pointX":480,"pointY":39.863967895507812},"width":966,"sublayerTransform":[1,0,0,0,0,1,0,0,0,0,1,0,0,0,0,1],"contentsRect":{"y":0,"x":0,"width":1,"height":1},"opacity":1,"edgeAntialiasingMask":0,"height":86,"hidden":false,"anchorPoint":{"pointX":0.5,"pointY":0.5}},"texture":"75BD6FF36F5358FE23CA21DC0E2B2B59"}]}]}]}},{"effects":[{"beginTime":0,"baseLayer":{"animations":[],"initialState":{"affineTransform":[1,0,0,1,0,0],"masksToBounds":false,"rotation":0,"scale":1,"position":{"pointX":514.89011573791504,"pointY":499.43682861328125},"width":968,"sublayerTransform":[1,0,0,0,0,1,0,0,0,0,1,0,0,0,0,1],"contentsRect":{"y":0,"x":0,"width":1,"height":1},"opacity":1,"edgeAntialiasingMask":251658240,"height":85,"hidden":false,"anchorPoint":{"pointX":0.5,"pointY":0.5}},"objectID":"2D2998DE-7084-4730-A789-BB46D87301FC","layers":[{"animations":[],"initialState":{"affineTransform":[1,0,0,1,0,0],"masksToBounds":false,"rotation":0,"scale":1,"position":{"pointX":481.10988426208496,"pointY":-72.93682861328125},"width":968,"sublayerTransform":[1,0,0,0,0,1,0,0,0,0,1,-0.00049229876906403734,0,0,0,1],"contentsRect":{"y":0,"x":0,"width":1,"height":1},"opacity":1,"edgeAntialiasingMask":251658240,"height":85,"hidden":false,"anchorPoint":{"pointX":0.49701434324595556,"pointY":-0.85808033662683825}},"layers":[{"animations":[{"additive":false,"timeOffset":0,"beginTime":1e-100,"repeatCount":0,"fillMode":"both","duration":0.001,"autoreverses":false,"animations":[{"additive":false,"timeOffset":0,"beginTime":0,"from":{"scalar":true},"repeatCount":0,"fillMode":"both","duration":0.0001,"autoreverses":false,"property":"hidden","to":{"scalar":false},"removedOnCompletion":true},{"additive":false,"timeOffset":0,"beginTime":0.0001,"from":{"scalar":false},"repeatCount":0,"fillMode":"forwards","duration":0.00089999999999999998,"autoreverses":false,"property":"hidden","to":{"scalar":false},"removedOnCompletion":true}],"removedOnCompletion":false}],"layers":[],"texturedRectangle":{"isBackgroundTexture":true,"singleTextureOpacity":1,"textureType":5,"textBaseline":0,"textXHeight":0,"isVerticalText":false},"initialState":{"affineTransform":[1,0,0,1,0,0],"masksToBounds":false,"rotation":0,"scale":1,"position":{"pointX":480.10988426208496,"pointY":38.56317138671875},"width":968,"sublayerTransform":[1,0,0,0,0,1,0,0,0,0,1,0,0,0,0,1],"contentsRect":{"y":0,"x":0,"width":1,"height":1},"opacity":1,"edgeAntialiasingMask":0,"height":85,"hidden":true,"anchorPoint":{"pointX":0.5,"pointY":0.5}},"texture":"2AC635A1B91F79381B7DC140DF8EC6FD"}]}]},"effects":[],"duration":0.001,"type":"buildIn","attributes":{"direction":0},"name":"apple:appear","objectID":"2D2998DE-7084-4730-A789-BB46D87301FC"}],"automaticPlay":false,"hyperlinks":[],"accessibility":[{"text":"equation.pdf","targetRectangle":{"y":460.93682861328125,"x":346.1990309553442,"width":20.787277030323764,"height":33.316556337194697}},{"text":"Given a Markov kernel ￼ can construct a chain ￼ by iterating over ￼","targetRectangle":{"y":354.33309936523438,"x":61.654824018478394,"width":707.51718353084277,"height":33.373817505419026}},{"text":"equation.pdf","targetRectangle":{"y":511.54714965820312,"x":348.41738891601562,"width":282.74505945299848,"height":25.38674860604101}},{"text":"The marginal law ￼ of ￼ after ￼ steps satisfies","targetRectangle":{"y":460.93682861328125,"x":131.65482401847839,"width":435.89900733167542,"height":33.316556337194697}},{"text":"equation.pdf","targetRectangle":{"y":195.43658447265625,"x":291.46875,"width":404.70209024355131,"height":23.811000000000007}},{"text":"equation.pdf","targetRectangle":{"y":408.95050048828125,"x":412.14752197265625,"width":163.77309745094021,"height":23.520248598083867}},{"text":"￼","targetRectangle":{"y":66.408382415771484,"x":964.57660043239594,"width":23.0390625,"height":28}},{"text":"Given a Markov chain defines a Markov kernel as the one step transition","targetRectangle":{"y":238.13603210449219,"x":97.764708280563354,"width":679.18399999999974,"height":26.361846923828125}},{"text":"equation.pdf","targetRectangle":{"y":460.93682861328125,"x":297.53482401847839,"width":18.502206936865832,"height":33.316556337194697}},{"text":"equation.pdf","targetRectangle":{"y":291.52666219037121,"x":280.09764494433477,"width":425.71490623288685,"height":23.810999999999979}},{"text":"Markov kernels v4: Markov chains","targetRectangle":{"y":56.908382415771484,"x":36,"width":578.44800000000009,"height":48.400146484375}},{"text":"equation.pdf","targetRectangle":{"y":634.04052734375,"x":296.219970703125,"width":436.3112914620815,"height":68.98475017285341}},{"text":"equation.pdf","targetRectangle":{"y":354.33309936523438,"x":696.35318048805425,"width":72.818827061266916,"height":33.373817505419026}},{"text":"equation.pdf","targetRectangle":{"y":354.33309936523438,"x":278.20082401847839,"width":17.931079439252358,"height":31.721952634437059}},{"text":"equation.pdf","targetRectangle":{"y":137.54168701171875,"x":623.94273072106353,"width":20.646280373831814,"height":31.721952634437059}},{"text":"equation.pdf","targetRectangle":{"y":137.54168701171875,"x":219.40470828056334,"width":153.93602244050032,"height":33.373817505419026}},{"text":"The joint law of ￼ ","targetRectangle":{"y":577.320068359375,"x":133.87459063529968,"width":337.97634477694891,"height":33.37381750541897}},{"text":"A Markov Chain ￼ is a stochastic process in ￼ such that ","targetRectangle":{"y":137.54168701171875,"x":62.764708280563354,"width":682.05630281433173,"height":33.373817505419026}},{"text":"equation.pdf","targetRectangle":{"y":577.320068359375,"x":282.22059063529969,"width":183.51434477694892,"height":33.37381750541897}},{"text":"equation.pdf","targetRectangle":{"y":460.93682861328125,"x":421.19430798566793,"width":7.4735233644859704,"height":31.721952634437059}},{"text":"equation.pdf","targetRectangle":{"y":354.33309936523438,"x":512.54590345773079,"width":20.787277030323708,"height":33.316556337194697}}],"baseLayer":{"animations":[],"initialState":{"affineTransform":[1,0,0,1,0,0],"masksToBounds":false,"rotation":0,"scale":1,"position":{"pointX":512,"pointY":384},"width":1024,"sublayerTransform":[1,0,0,0,0,1,0,0,0,0,1,0,0,0,0,1],"contentsRect":{"y":0,"x":0,"width":1,"height":1},"opacity":1,"edgeAntialiasingMask":251658240,"height":768,"hidden":false,"anchorPoint":{"pointX":0.5,"pointY":0.5}},"layers":[{"animations":[],"initialState":{"affineTransform":[1,0,0,1,0,0],"masksToBounds":false,"rotation":0,"scale":1,"position":{"pointX":512,"pointY":384},"width":1024,"sublayerTransform":[1,0,0,0,0,1,0,0,0,0,1,0,0,0,0,1],"contentsRect":{"y":0,"x":0,"width":1,"height":1},"opacity":1,"edgeAntialiasingMask":251658240,"height":768,"hidden":false,"anchorPoint":{"pointX":0.5,"pointY":0.5}},"layers":[{"animations":[],"initialState":{"affineTransform":[1,0,0,1,0,0],"masksToBounds":false,"rotation":0,"scale":1,"position":{"pointX":512,"pointY":384},"width":1024,"sublayerTransform":[1,0,0,0,0,1,0,0,0,0,1,0,0,0,0,1],"contentsRect":{"y":0,"x":0,"width":1,"height":1},"opacity":1,"edgeAntialiasingMask":251658240,"height":768,"hidden":false,"anchorPoint":{"pointX":0.5,"pointY":0.5}},"layers":[{"animations":[],"layers":[],"texturedRectangle":{"isBackgroundTexture":true,"singleTextureOpacity":1,"textureType":1,"textBaseline":0,"textXHeight":0,"isVerticalText":false},"initialState":{"affineTransform":[1,0,0,1,0,0],"masksToBounds":false,"rotation":0,"scale":1,"position":{"pointX":512,"pointY":384},"width":1024,"sublayerTransform":[1,0,0,0,0,1,0,0,0,0,1,0,0,0,0,1],"contentsRect":{"y":0,"x":0,"width":1,"height":1},"opacity":1,"edgeAntialiasingMask":0,"height":768,"hidden":false,"anchorPoint":{"pointX":0.5,"pointY":0.5}},"texture":"9251636AE7EC24F2536617C9E7909BA3"}]}]},{"animations":[],"initialState":{"affineTransform":[1,0,0,1,0,0],"masksToBounds":false,"rotation":0,"scale":1,"position":{"pointX":512,"pointY":384},"width":1024,"sublayerTransform":[1,0,0,0,0,1,0,0,0,0,1,0,0,0,0,1],"contentsRect":{"y":0,"x":0,"width":1,"height":1},"opacity":1,"edgeAntialiasingMask":251658240,"height":768,"hidden":false,"anchorPoint":{"pointX":0.5,"pointY":0.5}},"layers":[{"animations":[],"initialState":{"affineTransform":[1,0,0,1,0,0],"masksToBounds":false,"rotation":0,"scale":1,"position":{"pointX":321,"pointY":71.908382415771484},"width":578,"sublayerTransform":[1,0,0,0,0,1,0,0,0,0,1,0,0,0,0,1],"contentsRect":{"y":0,"x":0,"width":1,"height":1},"opacity":1,"edgeAntialiasingMask":251658240,"height":38,"hidden":false,"anchorPoint":{"pointX":0.5,"pointY":0.5}},"layers":[{"animations":[],"layers":[],"texturedRectangle":{"singleTextureOpacity":1,"textXHeight":0.640421052631579,"textBaseline":0.96012627451043375,"isBackgroundTexture":true,"isVerticalText":false,"textColor":[0.46666663885116577,0.113725446164608,0.46274513006210327,1],"textureType":6},"initialState":{"affineTransform":[1,0,0,1,0,0],"masksToBounds":false,"rotation":0,"scale":1,"position":{"pointX":294,"pointY":21.091617584228516},"width":578,"sublayerTransform":[1,0,0,0,0,1,0,0,0,0,1,0,0,0,0,1],"contentsRect":{"y":0,"x":0,"width":1,"height":1},"opacity":1,"edgeAntialiasingMask":0,"height":38,"hidden":false,"anchorPoint":{"pointX":0.5,"pointY":0.5}},"texture":"58B928AAF0171AFA33A1A9DB076B54DF"}]}]},{"animations":[],"initialState":{"affineTransform":[1,0,0,1,0,0],"masksToBounds":false,"rotation":0,"scale":1,"position":{"pointX":512,"pointY":384},"width":1024,"sublayerTransform":[1,0,0,0,0,1,0,0,0,0,1,0,0,0,0,1],"contentsRect":{"y":0,"x":0,"width":1,"height":1},"opacity":1,"edgeAntialiasingMask":251658240,"height":768,"hidden":false,"anchorPoint":{"pointX":0.5,"pointY":0.5}},"layers":[{"animations":[],"initialState":{"affineTransform":[1,0,0,1,0,0],"masksToBounds":false,"rotation":0,"scale":1,"position":{"pointX":972.57660043239594,"pointY":72.908382415771484},"width":26,"sublayerTransform":[1,0,0,0,0,1,0,0,0,0,1,0,0,0,0,1],"contentsRect":{"y":0,"x":0,"width":1,"height":1},"opacity":1,"edgeAntialiasingMask":251658240,"height":21,"hidden":false,"anchorPoint":{"pointX":0.5,"pointY":0.5}},"layers":[{"animations":[],"layers":[],"texturedRectangle":{"singleTextureOpacity":1,"textXHeight":0.8203125,"textBaseline":0.90393338884626118,"isBackgroundTexture":true,"isVerticalText":false,"textColor":[0.65252363681793213,0.66733616590499878,0.66081041097640991,1],"textureType":6},"initialState":{"affineTransform":[1,0,0,1,0,0],"masksToBounds":false,"rotation":0,"scale":1,"position":{"pointX":16.423399567604065,"pointY":18.091617584228516},"width":26,"sublayerTransform":[1,0,0,0,0,1,0,0,0,0,1,0,0,0,0,1],"contentsRect":{"y":0,"x":0,"width":1,"height":1},"opacity":1,"edgeAntialiasingMask":0,"height":21,"hidden":false,"anchorPoint":{"pointX":0.5,"pointY":0.5}},"texture":"95D7342E436EC3FA033869266AFFF539"}]}]},{"animations":[],"initialState":{"affineTransform":[1,0,0,1,0,0],"masksToBounds":false,"rotation":0,"scale":1,"position":{"pointX":512,"pointY":384},"width":1024,"sublayerTransform":[1,0,0,0,0,1,0,0,0,0,1,0,0,0,0,1],"contentsRect":{"y":0,"x":0,"width":1,"height":1},"opacity":1,"edgeAntialiasingMask":251658240,"height":768,"hidden":false,"anchorPoint":{"pointX":0.5,"pointY":0.5}},"layers":[{"animations":[],"initialState":{"affineTransform":[1,0,0,1,0,0],"masksToBounds":false,"rotation":0,"scale":1,"position":{"pointX":516,"pointY":179.04168701171875},"width":968,"sublayerTransform":[1,0,0,0,0,1,0,0,0,0,1,0,0,0,0,1],"contentsRect":{"y":0,"x":0,"width":1,"height":1},"opacity":1,"edgeAntialiasingMask":251658240,"height":91,"hidden":false,"anchorPoint":{"pointX":0.5,"pointY":0.5}},"objectID":"8EB51A19-E110-4214-8053-342AEA12F7AC","layers":[{"animations":[],"layers":[],"texturedRectangle":{"isBackgroundTexture":true,"singleTextureOpacity":1,"textureType":5,"textBaseline":0,"textXHeight":0,"isVerticalText":false},"initialState":{"affineTransform":[1,0,0,1,0,0],"masksToBounds":false,"rotation":0,"scale":1,"position":{"pointX":480,"pointY":41.95831298828125},"width":968,"sublayerTransform":[1,0,0,0,0,1,0,0,0,0,1,0,0,0,0,1],"contentsRect":{"y":0,"x":0,"width":1,"height":1},"opacity":1,"edgeAntialiasingMask":0,"height":91,"hidden":false,"anchorPoint":{"pointX":0.5,"pointY":0.5}},"texture":"DC9A3BA08A4D9EB735DA96258A475113"}]}]},{"animations":[],"initialState":{"affineTransform":[1,0,0,1,0,0],"masksToBounds":false,"rotation":0,"scale":1,"position":{"pointX":512,"pointY":384},"width":1024,"sublayerTransform":[1,0,0,0,0,1,0,0,0,0,1,0,0,0,0,1],"contentsRect":{"y":0,"x":0,"width":1,"height":1},"opacity":1,"edgeAntialiasingMask":251658240,"height":768,"hidden":false,"anchorPoint":{"pointX":0.5,"pointY":0.5}},"layers":[{"animations":[],"initialState":{"affineTransform":[1,0,0,1,0,0],"masksToBounds":false,"rotation":0,"scale":1,"position":{"pointX":514.89011573791504,"pointY":393.83309936523438},"width":968,"sublayerTransform":[1,0,0,0,0,1,0,0,0,0,1,0,0,0,0,1],"contentsRect":{"y":0,"x":0,"width":1,"height":1},"opacity":1,"edgeAntialiasingMask":251658240,"height":87,"hidden":false,"anchorPoint":{"pointX":0.5,"pointY":0.5}},"objectID":"6E97E328-7C58-4ECD-BD54-4E2DE3E7B534","layers":[{"animations":[],"layers":[],"texturedRectangle":{"isBackgroundTexture":true,"singleTextureOpacity":1,"textureType":5,"textBaseline":0,"textXHeight":0,"isVerticalText":false},"initialState":{"affineTransform":[1,0,0,1,0,0],"masksToBounds":false,"rotation":0,"scale":1,"position":{"pointX":480.10988426208496,"pointY":40.166900634765625},"width":968,"sublayerTransform":[1,0,0,0,0,1,0,0,0,0,1,0,0,0,0,1],"contentsRect":{"y":0,"x":0,"width":1,"height":1},"opacity":1,"edgeAntialiasingMask":0,"height":87,"hidden":false,"anchorPoint":{"pointX":0.5,"pointY":0.5}},"texture":"BF223A31E7255648FF4367CA0B6DC93E"}]}]},{"animations":[],"initialState":{"affineTransform":[1,0,0,1,0,0],"masksToBounds":false,"rotation":0,"scale":1,"position":{"pointX":512,"pointY":384},"width":1024,"sublayerTransform":[1,0,0,0,0,1,0,0,0,0,1,0,0,0,0,1],"contentsRect":{"y":0,"x":0,"width":1,"height":1},"opacity":1,"edgeAntialiasingMask":251658240,"height":768,"hidden":false,"anchorPoint":{"pointX":0.5,"pointY":0.5}},"layers":[{"animations":[],"initialState":{"affineTransform":[1,0,0,1,0,0],"masksToBounds":false,"rotation":0,"scale":1,"position":{"pointX":514.89011573791504,"pointY":499.43682861328125},"width":968,"sublayerTransform":[1,0,0,0,0,1,0,0,0,0,1,0,0,0,0,1],"contentsRect":{"y":0,"x":0,"width":1,"height":1},"opacity":1,"edgeAntialiasingMask":251658240,"height":85,"hidden":false,"anchorPoint":{"pointX":0.5,"pointY":0.5}},"objectID":"2D2998DE-7084-4730-A789-BB46D87301FC","layers":[{"animations":[],"layers":[],"texturedRectangle":{"isBackgroundTexture":true,"singleTextureOpacity":1,"textureType":5,"textBaseline":0,"textXHeight":0,"isVerticalText":false},"initialState":{"affineTransform":[1,0,0,1,0,0],"masksToBounds":false,"rotation":0,"scale":1,"position":{"pointX":480.10988426208496,"pointY":38.56317138671875},"width":968,"sublayerTransform":[1,0,0,0,0,1,0,0,0,0,1,0,0,0,0,1],"contentsRect":{"y":0,"x":0,"width":1,"height":1},"opacity":1,"edgeAntialiasingMask":0,"height":85,"hidden":true,"anchorPoint":{"pointX":0.5,"pointY":0.5}},"texture":"2AC635A1B91F79381B7DC140DF8EC6FD"}]}]},{"animations":[],"initialState":{"affineTransform":[1,0,0,1,0,0],"masksToBounds":false,"rotation":0,"scale":1,"position":{"pointX":512,"pointY":384},"width":1024,"sublayerTransform":[1,0,0,0,0,1,0,0,0,0,1,0,0,0,0,1],"contentsRect":{"y":0,"x":0,"width":1,"height":1},"opacity":1,"edgeAntialiasingMask":251658240,"height":768,"hidden":false,"anchorPoint":{"pointX":0.5,"pointY":0.5}},"layers":[{"animations":[],"initialState":{"affineTransform":[1,0,0,1,0,0],"masksToBounds":false,"rotation":0,"scale":1,"position":{"pointX":517.10988235473633,"pointY":640.820068359375},"width":968,"sublayerTransform":[1,0,0,0,0,1,0,0,0,0,1,0,0,0,0,1],"contentsRect":{"y":0,"x":0,"width":1,"height":1},"opacity":1,"edgeAntialiasingMask":251658240,"height":135,"hidden":false,"anchorPoint":{"pointX":0.5,"pointY":0.5}},"objectID":"32BD2261-3E37-460F-B23A-521CCBCDB33F","layers":[{"animations":[],"layers":[],"texturedRectangle":{"isBackgroundTexture":true,"singleTextureOpacity":1,"textureType":5,"textBaseline":0,"textXHeight":0,"isVerticalText":false},"initialState":{"affineTransform":[1,0,0,1,0,0],"masksToBounds":false,"rotation":0,"scale":1,"position":{"pointX":479.89011764526367,"pointY":64.179931640625},"width":968,"sublayerTransform":[1,0,0,0,0,1,0,0,0,0,1,0,0,0,0,1],"contentsRect":{"y":0,"x":0,"width":1,"height":1},"opacity":1,"edgeAntialiasingMask":0,"height":135,"hidden":true,"anchorPoint":{"pointX":0.5,"pointY":0.5}},"texture":"51362B679AAC4739143AF2ABA5836914"}]}]},{"animations":[],"initialState":{"affineTransform":[1,0,0,1,0,0],"masksToBounds":false,"rotation":0,"scale":1,"position":{"pointX":512,"pointY":384},"width":1024,"sublayerTransform":[1,0,0,0,0,1,0,0,0,0,1,0,0,0,0,1],"contentsRect":{"y":0,"x":0,"width":1,"height":1},"opacity":1,"edgeAntialiasingMask":251658240,"height":768,"hidden":false,"anchorPoint":{"pointX":0.5,"pointY":0.5}},"layers":[{"animations":[],"initialState":{"affineTransform":[1,0,0,1,0,0],"masksToBounds":false,"rotation":0,"scale":1,"position":{"pointX":515,"pointY":277.13603210449219},"width":966,"sublayerTransform":[1,0,0,0,0,1,0,0,0,0,1,0,0,0,0,1],"contentsRect":{"y":0,"x":0,"width":1,"height":1},"opacity":1,"edgeAntialiasingMask":251658240,"height":86,"hidden":false,"anchorPoint":{"pointX":0.5,"pointY":0.5}},"objectID":"98B8DDAD-86E4-4739-A0DA-7C1153DB4A89","layers":[{"animations":[],"layers":[],"texturedRectangle":{"isBackgroundTexture":true,"singleTextureOpacity":1,"textureType":5,"textBaseline":0,"textXHeight":0,"isVerticalText":false},"initialState":{"affineTransform":[1,0,0,1,0,0],"masksToBounds":false,"rotation":0,"scale":1,"position":{"pointX":480,"pointY":39.863967895507812},"width":966,"sublayerTransform":[1,0,0,0,0,1,0,0,0,0,1,0,0,0,0,1],"contentsRect":{"y":0,"x":0,"width":1,"height":1},"opacity":1,"edgeAntialiasingMask":0,"height":86,"hidden":false,"anchorPoint":{"pointX":0.5,"pointY":0.5}},"texture":"75BD6FF36F5358FE23CA21DC0E2B2B59"}]}]}]}},{"effects":[{"beginTime":0,"baseLayer":{"animations":[],"initialState":{"affineTransform":[1,0,0,1,0,0],"masksToBounds":false,"rotation":0,"scale":1,"position":{"pointX":517.10988235473633,"pointY":640.820068359375},"width":968,"sublayerTransform":[1,0,0,0,0,1,0,0,0,0,1,0,0,0,0,1],"contentsRect":{"y":0,"x":0,"width":1,"height":1},"opacity":1,"edgeAntialiasingMask":251658240,"height":135,"hidden":false,"anchorPoint":{"pointX":0.5,"pointY":0.5}},"objectID":"32BD2261-3E37-460F-B23A-521CCBCDB33F","layers":[{"animations":[],"initialState":{"affineTransform":[1,0,0,1,0,0],"masksToBounds":false,"rotation":0,"scale":1,"position":{"pointX":478.89011764526367,"pointY":-189.320068359375},"width":968,"sublayerTransform":[1,0,0,0,0,1,0,0,0,0,1,-0.00049229876906403734,0,0,0,1],"contentsRect":{"y":0,"x":0,"width":1,"height":1},"opacity":1,"edgeAntialiasingMask":251658240,"height":135,"hidden":false,"anchorPoint":{"pointX":0.49472119591452857,"pointY":-1.4023708767361112}},"layers":[{"animations":[{"additive":false,"timeOffset":0,"beginTime":1e-100,"repeatCount":0,"fillMode":"both","duration":0.001,"autoreverses":false,"animations":[{"additive":false,"timeOffset":0,"beginTime":0,"from":{"scalar":true},"repeatCount":0,"fillMode":"both","duration":0.0001,"autoreverses":false,"property":"hidden","to":{"scalar":false},"removedOnCompletion":true},{"additive":false,"timeOffset":0,"beginTime":0.0001,"from":{"scalar":false},"repeatCount":0,"fillMode":"forwards","duration":0.00089999999999999998,"autoreverses":false,"property":"hidden","to":{"scalar":false},"removedOnCompletion":true}],"removedOnCompletion":false}],"layers":[],"texturedRectangle":{"isBackgroundTexture":true,"singleTextureOpacity":1,"textureType":5,"textBaseline":0,"textXHeight":0,"isVerticalText":false},"initialState":{"affineTransform":[1,0,0,1,0,0],"masksToBounds":false,"rotation":0,"scale":1,"position":{"pointX":479.89011764526367,"pointY":64.179931640625},"width":968,"sublayerTransform":[1,0,0,0,0,1,0,0,0,0,1,0,0,0,0,1],"contentsRect":{"y":0,"x":0,"width":1,"height":1},"opacity":1,"edgeAntialiasingMask":0,"height":135,"hidden":true,"anchorPoint":{"pointX":0.5,"pointY":0.5}},"texture":"51362B679AAC4739143AF2ABA5836914"}]}]},"effects":[],"duration":0.001,"type":"buildIn","attributes":{"direction":0},"name":"apple:appear","objectID":"32BD2261-3E37-460F-B23A-521CCBCDB33F"}],"automaticPlay":false,"hyperlinks":[],"accessibility":[{"text":"equation.pdf","targetRectangle":{"y":460.93682861328125,"x":346.1990309553442,"width":20.787277030323764,"height":33.316556337194697}},{"text":"Given a Markov kernel ￼ can construct a chain ￼ by iterating over ￼","targetRectangle":{"y":354.33309936523438,"x":61.654824018478394,"width":707.51718353084277,"height":33.373817505419026}},{"text":"equation.pdf","targetRectangle":{"y":511.54714965820312,"x":348.41738891601562,"width":282.74505945299848,"height":25.38674860604101}},{"text":"The marginal law ￼ of ￼ after ￼ steps satisfies","targetRectangle":{"y":460.93682861328125,"x":131.65482401847839,"width":435.89900733167542,"height":33.316556337194697}},{"text":"equation.pdf","targetRectangle":{"y":195.43658447265625,"x":291.46875,"width":404.70209024355131,"height":23.811000000000007}},{"text":"equation.pdf","targetRectangle":{"y":408.95050048828125,"x":412.14752197265625,"width":163.77309745094021,"height":23.520248598083867}},{"text":"￼","targetRectangle":{"y":66.408382415771484,"x":964.57660043239594,"width":23.0390625,"height":28}},{"text":"Given a Markov chain defines a Markov kernel as the one step transition","targetRectangle":{"y":238.13603210449219,"x":97.764708280563354,"width":679.18399999999974,"height":26.361846923828125}},{"text":"equation.pdf","targetRectangle":{"y":460.93682861328125,"x":297.53482401847839,"width":18.502206936865832,"height":33.316556337194697}},{"text":"equation.pdf","targetRectangle":{"y":291.52666219037121,"x":280.09764494433477,"width":425.71490623288685,"height":23.810999999999979}},{"text":"Markov kernels v4: Markov chains","targetRectangle":{"y":56.908382415771484,"x":36,"width":578.44800000000009,"height":48.400146484375}},{"text":"equation.pdf","targetRectangle":{"y":634.04052734375,"x":296.219970703125,"width":436.3112914620815,"height":68.98475017285341}},{"text":"equation.pdf","targetRectangle":{"y":354.33309936523438,"x":696.35318048805425,"width":72.818827061266916,"height":33.373817505419026}},{"text":"equation.pdf","targetRectangle":{"y":354.33309936523438,"x":278.20082401847839,"width":17.931079439252358,"height":31.721952634437059}},{"text":"equation.pdf","targetRectangle":{"y":137.54168701171875,"x":623.94273072106353,"width":20.646280373831814,"height":31.721952634437059}},{"text":"equation.pdf","targetRectangle":{"y":137.54168701171875,"x":219.40470828056334,"width":153.93602244050032,"height":33.373817505419026}},{"text":"The joint law of ￼ ","targetRectangle":{"y":577.320068359375,"x":133.87459063529968,"width":337.97634477694891,"height":33.37381750541897}},{"text":"A Markov Chain ￼ is a stochastic process in ￼ such that ","targetRectangle":{"y":137.54168701171875,"x":62.764708280563354,"width":682.05630281433173,"height":33.373817505419026}},{"text":"equation.pdf","targetRectangle":{"y":577.320068359375,"x":282.22059063529969,"width":183.51434477694892,"height":33.37381750541897}},{"text":"equation.pdf","targetRectangle":{"y":460.93682861328125,"x":421.19430798566793,"width":7.4735233644859704,"height":31.721952634437059}},{"text":"equation.pdf","targetRectangle":{"y":354.33309936523438,"x":512.54590345773079,"width":20.787277030323708,"height":33.316556337194697}}],"baseLayer":{"animations":[],"initialState":{"affineTransform":[1,0,0,1,0,0],"masksToBounds":false,"rotation":0,"scale":1,"position":{"pointX":512,"pointY":384},"width":1024,"sublayerTransform":[1,0,0,0,0,1,0,0,0,0,1,0,0,0,0,1],"contentsRect":{"y":0,"x":0,"width":1,"height":1},"opacity":1,"edgeAntialiasingMask":251658240,"height":768,"hidden":false,"anchorPoint":{"pointX":0.5,"pointY":0.5}},"layers":[{"animations":[],"initialState":{"affineTransform":[1,0,0,1,0,0],"masksToBounds":false,"rotation":0,"scale":1,"position":{"pointX":512,"pointY":384},"width":1024,"sublayerTransform":[1,0,0,0,0,1,0,0,0,0,1,0,0,0,0,1],"contentsRect":{"y":0,"x":0,"width":1,"height":1},"opacity":1,"edgeAntialiasingMask":251658240,"height":768,"hidden":false,"anchorPoint":{"pointX":0.5,"pointY":0.5}},"layers":[{"animations":[],"initialState":{"affineTransform":[1,0,0,1,0,0],"masksToBounds":false,"rotation":0,"scale":1,"position":{"pointX":512,"pointY":384},"width":1024,"sublayerTransform":[1,0,0,0,0,1,0,0,0,0,1,0,0,0,0,1],"contentsRect":{"y":0,"x":0,"width":1,"height":1},"opacity":1,"edgeAntialiasingMask":251658240,"height":768,"hidden":false,"anchorPoint":{"pointX":0.5,"pointY":0.5}},"layers":[{"animations":[],"layers":[],"texturedRectangle":{"isBackgroundTexture":true,"singleTextureOpacity":1,"textureType":1,"textBaseline":0,"textXHeight":0,"isVerticalText":false},"initialState":{"affineTransform":[1,0,0,1,0,0],"masksToBounds":false,"rotation":0,"scale":1,"position":{"pointX":512,"pointY":384},"width":1024,"sublayerTransform":[1,0,0,0,0,1,0,0,0,0,1,0,0,0,0,1],"contentsRect":{"y":0,"x":0,"width":1,"height":1},"opacity":1,"edgeAntialiasingMask":0,"height":768,"hidden":false,"anchorPoint":{"pointX":0.5,"pointY":0.5}},"texture":"9251636AE7EC24F2536617C9E7909BA3"}]}]},{"animations":[],"initialState":{"affineTransform":[1,0,0,1,0,0],"masksToBounds":false,"rotation":0,"scale":1,"position":{"pointX":512,"pointY":384},"width":1024,"sublayerTransform":[1,0,0,0,0,1,0,0,0,0,1,0,0,0,0,1],"contentsRect":{"y":0,"x":0,"width":1,"height":1},"opacity":1,"edgeAntialiasingMask":251658240,"height":768,"hidden":false,"anchorPoint":{"pointX":0.5,"pointY":0.5}},"layers":[{"animations":[],"initialState":{"affineTransform":[1,0,0,1,0,0],"masksToBounds":false,"rotation":0,"scale":1,"position":{"pointX":321,"pointY":71.908382415771484},"width":578,"sublayerTransform":[1,0,0,0,0,1,0,0,0,0,1,0,0,0,0,1],"contentsRect":{"y":0,"x":0,"width":1,"height":1},"opacity":1,"edgeAntialiasingMask":251658240,"height":38,"hidden":false,"anchorPoint":{"pointX":0.5,"pointY":0.5}},"layers":[{"animations":[],"layers":[],"texturedRectangle":{"singleTextureOpacity":1,"textXHeight":0.640421052631579,"textBaseline":0.96012627451043375,"isBackgroundTexture":true,"isVerticalText":false,"textColor":[0.46666663885116577,0.113725446164608,0.46274513006210327,1],"textureType":6},"initialState":{"affineTransform":[1,0,0,1,0,0],"masksToBounds":false,"rotation":0,"scale":1,"position":{"pointX":294,"pointY":21.091617584228516},"width":578,"sublayerTransform":[1,0,0,0,0,1,0,0,0,0,1,0,0,0,0,1],"contentsRect":{"y":0,"x":0,"width":1,"height":1},"opacity":1,"edgeAntialiasingMask":0,"height":38,"hidden":false,"anchorPoint":{"pointX":0.5,"pointY":0.5}},"texture":"58B928AAF0171AFA33A1A9DB076B54DF"}]}]},{"animations":[],"initialState":{"affineTransform":[1,0,0,1,0,0],"masksToBounds":false,"rotation":0,"scale":1,"position":{"pointX":512,"pointY":384},"width":1024,"sublayerTransform":[1,0,0,0,0,1,0,0,0,0,1,0,0,0,0,1],"contentsRect":{"y":0,"x":0,"width":1,"height":1},"opacity":1,"edgeAntialiasingMask":251658240,"height":768,"hidden":false,"anchorPoint":{"pointX":0.5,"pointY":0.5}},"layers":[{"animations":[],"initialState":{"affineTransform":[1,0,0,1,0,0],"masksToBounds":false,"rotation":0,"scale":1,"position":{"pointX":972.57660043239594,"pointY":72.908382415771484},"width":26,"sublayerTransform":[1,0,0,0,0,1,0,0,0,0,1,0,0,0,0,1],"contentsRect":{"y":0,"x":0,"width":1,"height":1},"opacity":1,"edgeAntialiasingMask":251658240,"height":21,"hidden":false,"anchorPoint":{"pointX":0.5,"pointY":0.5}},"layers":[{"animations":[],"layers":[],"texturedRectangle":{"singleTextureOpacity":1,"textXHeight":0.8203125,"textBaseline":0.90393338884626118,"isBackgroundTexture":true,"isVerticalText":false,"textColor":[0.65252363681793213,0.66733616590499878,0.66081041097640991,1],"textureType":6},"initialState":{"affineTransform":[1,0,0,1,0,0],"masksToBounds":false,"rotation":0,"scale":1,"position":{"pointX":16.423399567604065,"pointY":18.091617584228516},"width":26,"sublayerTransform":[1,0,0,0,0,1,0,0,0,0,1,0,0,0,0,1],"contentsRect":{"y":0,"x":0,"width":1,"height":1},"opacity":1,"edgeAntialiasingMask":0,"height":21,"hidden":false,"anchorPoint":{"pointX":0.5,"pointY":0.5}},"texture":"95D7342E436EC3FA033869266AFFF539"}]}]},{"animations":[],"initialState":{"affineTransform":[1,0,0,1,0,0],"masksToBounds":false,"rotation":0,"scale":1,"position":{"pointX":512,"pointY":384},"width":1024,"sublayerTransform":[1,0,0,0,0,1,0,0,0,0,1,0,0,0,0,1],"contentsRect":{"y":0,"x":0,"width":1,"height":1},"opacity":1,"edgeAntialiasingMask":251658240,"height":768,"hidden":false,"anchorPoint":{"pointX":0.5,"pointY":0.5}},"layers":[{"animations":[],"initialState":{"affineTransform":[1,0,0,1,0,0],"masksToBounds":false,"rotation":0,"scale":1,"position":{"pointX":516,"pointY":179.04168701171875},"width":968,"sublayerTransform":[1,0,0,0,0,1,0,0,0,0,1,0,0,0,0,1],"contentsRect":{"y":0,"x":0,"width":1,"height":1},"opacity":1,"edgeAntialiasingMask":251658240,"height":91,"hidden":false,"anchorPoint":{"pointX":0.5,"pointY":0.5}},"objectID":"8EB51A19-E110-4214-8053-342AEA12F7AC","layers":[{"animations":[],"layers":[],"texturedRectangle":{"isBackgroundTexture":true,"singleTextureOpacity":1,"textureType":5,"textBaseline":0,"textXHeight":0,"isVerticalText":false},"initialState":{"affineTransform":[1,0,0,1,0,0],"masksToBounds":false,"rotation":0,"scale":1,"position":{"pointX":480,"pointY":41.95831298828125},"width":968,"sublayerTransform":[1,0,0,0,0,1,0,0,0,0,1,0,0,0,0,1],"contentsRect":{"y":0,"x":0,"width":1,"height":1},"opacity":1,"edgeAntialiasingMask":0,"height":91,"hidden":false,"anchorPoint":{"pointX":0.5,"pointY":0.5}},"texture":"DC9A3BA08A4D9EB735DA96258A475113"}]}]},{"animations":[],"initialState":{"affineTransform":[1,0,0,1,0,0],"masksToBounds":false,"rotation":0,"scale":1,"position":{"pointX":512,"pointY":384},"width":1024,"sublayerTransform":[1,0,0,0,0,1,0,0,0,0,1,0,0,0,0,1],"contentsRect":{"y":0,"x":0,"width":1,"height":1},"opacity":1,"edgeAntialiasingMask":251658240,"height":768,"hidden":false,"anchorPoint":{"pointX":0.5,"pointY":0.5}},"layers":[{"animations":[],"initialState":{"affineTransform":[1,0,0,1,0,0],"masksToBounds":false,"rotation":0,"scale":1,"position":{"pointX":514.89011573791504,"pointY":393.83309936523438},"width":968,"sublayerTransform":[1,0,0,0,0,1,0,0,0,0,1,0,0,0,0,1],"contentsRect":{"y":0,"x":0,"width":1,"height":1},"opacity":1,"edgeAntialiasingMask":251658240,"height":87,"hidden":false,"anchorPoint":{"pointX":0.5,"pointY":0.5}},"objectID":"6E97E328-7C58-4ECD-BD54-4E2DE3E7B534","layers":[{"animations":[],"layers":[],"texturedRectangle":{"isBackgroundTexture":true,"singleTextureOpacity":1,"textureType":5,"textBaseline":0,"textXHeight":0,"isVerticalText":false},"initialState":{"affineTransform":[1,0,0,1,0,0],"masksToBounds":false,"rotation":0,"scale":1,"position":{"pointX":480.10988426208496,"pointY":40.166900634765625},"width":968,"sublayerTransform":[1,0,0,0,0,1,0,0,0,0,1,0,0,0,0,1],"contentsRect":{"y":0,"x":0,"width":1,"height":1},"opacity":1,"edgeAntialiasingMask":0,"height":87,"hidden":false,"anchorPoint":{"pointX":0.5,"pointY":0.5}},"texture":"BF223A31E7255648FF4367CA0B6DC93E"}]}]},{"animations":[],"initialState":{"affineTransform":[1,0,0,1,0,0],"masksToBounds":false,"rotation":0,"scale":1,"position":{"pointX":512,"pointY":384},"width":1024,"sublayerTransform":[1,0,0,0,0,1,0,0,0,0,1,0,0,0,0,1],"contentsRect":{"y":0,"x":0,"width":1,"height":1},"opacity":1,"edgeAntialiasingMask":251658240,"height":768,"hidden":false,"anchorPoint":{"pointX":0.5,"pointY":0.5}},"layers":[{"animations":[],"initialState":{"affineTransform":[1,0,0,1,0,0],"masksToBounds":false,"rotation":0,"scale":1,"position":{"pointX":514.89011573791504,"pointY":499.43682861328125},"width":968,"sublayerTransform":[1,0,0,0,0,1,0,0,0,0,1,0,0,0,0,1],"contentsRect":{"y":0,"x":0,"width":1,"height":1},"opacity":1,"edgeAntialiasingMask":251658240,"height":85,"hidden":false,"anchorPoint":{"pointX":0.5,"pointY":0.5}},"objectID":"2D2998DE-7084-4730-A789-BB46D87301FC","layers":[{"animations":[],"layers":[],"texturedRectangle":{"isBackgroundTexture":true,"singleTextureOpacity":1,"textureType":5,"textBaseline":0,"textXHeight":0,"isVerticalText":false},"initialState":{"affineTransform":[1,0,0,1,0,0],"masksToBounds":false,"rotation":0,"scale":1,"position":{"pointX":480.10988426208496,"pointY":38.56317138671875},"width":968,"sublayerTransform":[1,0,0,0,0,1,0,0,0,0,1,0,0,0,0,1],"contentsRect":{"y":0,"x":0,"width":1,"height":1},"opacity":1,"edgeAntialiasingMask":0,"height":85,"hidden":false,"anchorPoint":{"pointX":0.5,"pointY":0.5}},"texture":"2AC635A1B91F79381B7DC140DF8EC6FD"}]}]},{"animations":[],"initialState":{"affineTransform":[1,0,0,1,0,0],"masksToBounds":false,"rotation":0,"scale":1,"position":{"pointX":512,"pointY":384},"width":1024,"sublayerTransform":[1,0,0,0,0,1,0,0,0,0,1,0,0,0,0,1],"contentsRect":{"y":0,"x":0,"width":1,"height":1},"opacity":1,"edgeAntialiasingMask":251658240,"height":768,"hidden":false,"anchorPoint":{"pointX":0.5,"pointY":0.5}},"layers":[{"animations":[],"initialState":{"affineTransform":[1,0,0,1,0,0],"masksToBounds":false,"rotation":0,"scale":1,"position":{"pointX":517.10988235473633,"pointY":640.820068359375},"width":968,"sublayerTransform":[1,0,0,0,0,1,0,0,0,0,1,0,0,0,0,1],"contentsRect":{"y":0,"x":0,"width":1,"height":1},"opacity":1,"edgeAntialiasingMask":251658240,"height":135,"hidden":false,"anchorPoint":{"pointX":0.5,"pointY":0.5}},"objectID":"32BD2261-3E37-460F-B23A-521CCBCDB33F","layers":[{"animations":[],"layers":[],"texturedRectangle":{"isBackgroundTexture":true,"singleTextureOpacity":1,"textureType":5,"textBaseline":0,"textXHeight":0,"isVerticalText":false},"initialState":{"affineTransform":[1,0,0,1,0,0],"masksToBounds":false,"rotation":0,"scale":1,"position":{"pointX":479.89011764526367,"pointY":64.179931640625},"width":968,"sublayerTransform":[1,0,0,0,0,1,0,0,0,0,1,0,0,0,0,1],"contentsRect":{"y":0,"x":0,"width":1,"height":1},"opacity":1,"edgeAntialiasingMask":0,"height":135,"hidden":true,"anchorPoint":{"pointX":0.5,"pointY":0.5}},"texture":"51362B679AAC4739143AF2ABA5836914"}]}]},{"animations":[],"initialState":{"affineTransform":[1,0,0,1,0,0],"masksToBounds":false,"rotation":0,"scale":1,"position":{"pointX":512,"pointY":384},"width":1024,"sublayerTransform":[1,0,0,0,0,1,0,0,0,0,1,0,0,0,0,1],"contentsRect":{"y":0,"x":0,"width":1,"height":1},"opacity":1,"edgeAntialiasingMask":251658240,"height":768,"hidden":false,"anchorPoint":{"pointX":0.5,"pointY":0.5}},"layers":[{"animations":[],"initialState":{"affineTransform":[1,0,0,1,0,0],"masksToBounds":false,"rotation":0,"scale":1,"position":{"pointX":515,"pointY":277.13603210449219},"width":966,"sublayerTransform":[1,0,0,0,0,1,0,0,0,0,1,0,0,0,0,1],"contentsRect":{"y":0,"x":0,"width":1,"height":1},"opacity":1,"edgeAntialiasingMask":251658240,"height":86,"hidden":false,"anchorPoint":{"pointX":0.5,"pointY":0.5}},"objectID":"98B8DDAD-86E4-4739-A0DA-7C1153DB4A89","layers":[{"animations":[],"layers":[],"texturedRectangle":{"isBackgroundTexture":true,"singleTextureOpacity":1,"textureType":5,"textBaseline":0,"textXHeight":0,"isVerticalText":false},"initialState":{"affineTransform":[1,0,0,1,0,0],"masksToBounds":false,"rotation":0,"scale":1,"position":{"pointX":480,"pointY":39.863967895507812},"width":966,"sublayerTransform":[1,0,0,0,0,1,0,0,0,0,1,0,0,0,0,1],"contentsRect":{"y":0,"x":0,"width":1,"height":1},"opacity":1,"edgeAntialiasingMask":0,"height":86,"hidden":false,"anchorPoint":{"pointX":0.5,"pointY":0.5}},"texture":"75BD6FF36F5358FE23CA21DC0E2B2B59"}]}]}]}},{"effects":[{"beginTime":0,"baseLayer":{"animations":[],"initialState":{"affineTransform":[1,0,0,1,0,0],"masksToBounds":false,"rotation":0,"scale":1,"position":{"pointX":512,"pointY":384},"width":1024,"sublayerTransform":[1,0,0,0,0,1,0,0,0,0,1,0,0,0,0,1],"contentsRect":{"y":0,"x":0,"width":1,"height":1},"opacity":1,"edgeAntialiasingMask":251658240,"height":768,"hidden":false,"anchorPoint":{"pointX":0.5,"pointY":0.5}},"objectID":"0","layers":[{"animations":[],"initialState":{"affineTransform":[1,0,0,1,0,0],"masksToBounds":false,"rotation":0,"scale":1,"position":{"pointX":512,"pointY":384},"width":1024,"sublayerTransform":[1,0,0,0,0,1,0,0,0,0,1,-0.00049229876906403734,0,0,0,1],"contentsRect":{"y":0,"x":0,"width":1,"height":1},"opacity":1,"edgeAntialiasingMask":251658240,"height":768,"hidden":false,"anchorPoint":{"pointX":0.5,"pointY":0.5}},"layers":[{"animations":[],"layers":[],"texturedRectangle":{"isBackgroundTexture":false,"singleTextureOpacity":1,"textureType":0,"textBaseline":0,"textXHeight":0,"isVerticalText":false},"initialState":{"affineTransform":[1,0,0,1,0,0],"masksToBounds":false,"rotation":0,"scale":1,"position":{"pointX":512,"pointY":384},"width":1024,"sublayerTransform":[1,0,0,0,0,1,0,0,0,0,1,0,0,0,0,1],"contentsRect":{"y":0,"x":0,"width":1,"height":1},"opacity":1,"edgeAntialiasingMask":0,"height":768,"hidden":false,"anchorPoint":{"pointX":0.5,"pointY":0.5}},"texture":"C393C2EE41E57BBAC6C8BC0FFE7B88CA"},{"animations":[{"additive":false,"timeOffset":0,"beginTime":0,"from":{"scalar":false},"repeatCount":0,"fillMode":"both","duration":0.001,"autoreverses":false,"property":"hidden","to":{"scalar":true},"removedOnCompletion":false}],"layers":[],"texturedRectangle":{"isBackgroundTexture":false,"singleTextureOpacity":1,"textureType":0,"textBaseline":0,"textXHeight":0,"isVerticalText":false},"initialState":{"affineTransform":[1,0,0,1,0,0],"masksToBounds":false,"rotation":0,"scale":1,"position":{"pointX":512,"pointY":384},"width":1024,"sublayerTransform":[1,0,0,0,0,1,0,0,0,0,1,0,0,0,0,1],"contentsRect":{"y":0,"x":0,"width":1,"height":1},"opacity":1,"edgeAntialiasingMask":0,"height":768,"hidden":false,"anchorPoint":{"pointX":0.5,"pointY":0.5}},"texture":"D0EB9A94DA96765B0A159C469B4E3EAB"}]}]},"effects":[],"duration":0.001,"type":"transition","attributes":{"direction":0},"name":"none","objectID":"0"}],"automaticPlay":false,"hyperlinks":[],"accessibility":[{"text":"equation.pdf","targetRectangle":{"y":460.93682861328125,"x":346.1990309553442,"width":20.787277030323764,"height":33.316556337194697}},{"text":"Given a Markov kernel ￼ can construct a chain ￼ by iterating over ￼","targetRectangle":{"y":354.33309936523438,"x":61.654824018478394,"width":707.51718353084277,"height":33.373817505419026}},{"text":"equation.pdf","targetRectangle":{"y":511.54714965820312,"x":348.41738891601562,"width":282.74505945299848,"height":25.38674860604101}},{"text":"The marginal law ￼ of ￼ after ￼ steps satisfies","targetRectangle":{"y":460.93682861328125,"x":131.65482401847839,"width":435.89900733167542,"height":33.316556337194697}},{"text":"equation.pdf","targetRectangle":{"y":195.43658447265625,"x":291.46875,"width":404.70209024355131,"height":23.811000000000007}},{"text":"equation.pdf","targetRectangle":{"y":408.95050048828125,"x":412.14752197265625,"width":163.77309745094021,"height":23.520248598083867}},{"text":"￼","targetRectangle":{"y":66.408382415771484,"x":964.57660043239594,"width":23.0390625,"height":28}},{"text":"Given a Markov chain defines a Markov kernel as the one step transition","targetRectangle":{"y":238.13603210449219,"x":97.764708280563354,"width":679.18399999999974,"height":26.361846923828125}},{"text":"equation.pdf","targetRectangle":{"y":460.93682861328125,"x":297.53482401847839,"width":18.502206936865832,"height":33.316556337194697}},{"text":"equation.pdf","targetRectangle":{"y":291.52666219037121,"x":280.09764494433477,"width":425.71490623288685,"height":23.810999999999979}},{"text":"Markov kernels v4: Markov chains","targetRectangle":{"y":56.908382415771484,"x":36,"width":578.44800000000009,"height":48.400146484375}},{"text":"equation.pdf","targetRectangle":{"y":634.04052734375,"x":296.219970703125,"width":436.3112914620815,"height":68.98475017285341}},{"text":"equation.pdf","targetRectangle":{"y":354.33309936523438,"x":696.35318048805425,"width":72.818827061266916,"height":33.373817505419026}},{"text":"equation.pdf","targetRectangle":{"y":354.33309936523438,"x":278.20082401847839,"width":17.931079439252358,"height":31.721952634437059}},{"text":"equation.pdf","targetRectangle":{"y":137.54168701171875,"x":623.94273072106353,"width":20.646280373831814,"height":31.721952634437059}},{"text":"equation.pdf","targetRectangle":{"y":137.54168701171875,"x":219.40470828056334,"width":153.93602244050032,"height":33.373817505419026}},{"text":"The joint law of ￼ ","targetRectangle":{"y":577.320068359375,"x":133.87459063529968,"width":337.97634477694891,"height":33.37381750541897}},{"text":"A Markov Chain ￼ is a stochastic process in ￼ such that ","targetRectangle":{"y":137.54168701171875,"x":62.764708280563354,"width":682.05630281433173,"height":33.373817505419026}},{"text":"equation.pdf","targetRectangle":{"y":577.320068359375,"x":282.22059063529969,"width":183.51434477694892,"height":33.37381750541897}},{"text":"equation.pdf","targetRectangle":{"y":460.93682861328125,"x":421.19430798566793,"width":7.4735233644859704,"height":31.721952634437059}},{"text":"equation.pdf","targetRectangle":{"y":354.33309936523438,"x":512.54590345773079,"width":20.787277030323708,"height":33.316556337194697}}],"baseLayer":{"animations":[],"initialState":{"affineTransform":[1,0,0,1,0,0],"masksToBounds":false,"rotation":0,"scale":1,"position":{"pointX":512,"pointY":384},"width":1024,"sublayerTransform":[1,0,0,0,0,1,0,0,0,0,1,0,0,0,0,1],"contentsRect":{"y":0,"x":0,"width":1,"height":1},"opacity":1,"edgeAntialiasingMask":251658240,"height":768,"hidden":false,"anchorPoint":{"pointX":0.5,"pointY":0.5}},"objectID":"0","layers":[{"animations":[],"initialState":{"affineTransform":[1,0,0,1,0,0],"masksToBounds":false,"rotation":0,"scale":1,"position":{"pointX":512,"pointY":384},"width":1024,"sublayerTransform":[1,0,0,0,0,1,0,0,0,0,1,-0.00049229876906403734,0,0,0,1],"contentsRect":{"y":0,"x":0,"width":1,"height":1},"opacity":1,"edgeAntialiasingMask":251658240,"height":768,"hidden":false,"anchorPoint":{"pointX":0.5,"pointY":0.5}},"layers":[{"animations":[],"layers":[],"texturedRectangle":{"isBackgroundTexture":false,"singleTextureOpacity":1,"textureType":0,"textBaseline":0,"textXHeight":0,"isVerticalText":false},"initialState":{"affineTransform":[1,0,0,1,0,0],"masksToBounds":false,"rotation":0,"scale":1,"position":{"pointX":512,"pointY":384},"width":1024,"sublayerTransform":[1,0,0,0,0,1,0,0,0,0,1,0,0,0,0,1],"contentsRect":{"y":0,"x":0,"width":1,"height":1},"opacity":1,"edgeAntialiasingMask":0,"height":768,"hidden":false,"anchorPoint":{"pointX":0.5,"pointY":0.5}},"texture":"D0EB9A94DA96765B0A159C469B4E3EAB"}]}]}}]}